Workbook

Sheet README
A1: IFI Gatehouse: rate book (REFERENCE, FICTIONAL RATES) - layout v2, 2.2.0
A2: Purpose | B2: DEMO FIXTURE. Every rate and price here is a fictional reference estimate, not any company's real rates. Safe for the repo and demo. Real rates go in a separate private copy of the blank template.
A3: Principle | B3: The model reads plans. Code calculates quantities. A person enters every dollar figure and every production rate. No dollar value is ever written by a model.
A5: How code fills it | B5: Quantities come only from the deterministic takeoff. A rate book handed to Gatehouse must leave Takeoff_In D:G EMPTY; an inspection export may fill them. Match rows by the key in column A.
A6: Keys | B6: M01 to M40 and M42 to M44 = material item_id (M41 is retired); S01 = core-drilling service. D01 to D12 = labor drivers. Keys are permanent; never renumber or reuse one. Add new keys at the bottom of Takeoff_In and the same ID in Materials.
A7: Layout rule | B7: Header is row 1 on every data sheet. No merged cells, no blank header cells. Read by header name, not by column letter.
A8: Reference columns | B8: Layout v2 carries no quantities of any kind. Quantities come only from the deterministic takeoff.
A10: What you fill
A11: Materials | B11: unit_price, vendor, price_date, source_url_or_sku, overage_pct. Add or rename materials freely; keep item_id unique and matched to a Takeoff_In key.
A12: Roles | B12: Base wage and burden per role. Loaded rate computes.
A13: Crews | B13: Headcount per role. Loaded crew rate computes.
A14: Labor | B14: For each task: crew_id and production_rate (units per crew-hour). Driver quantity pulls from Takeoff_In. Labor cost = quantity / rate x crew rate.
A15: Equipment | B15: Owned or rented, rate and basis, days or units for base and alt, fuel, delivery.
A16: Mobilization_Other | B16: Trips, mileage, per diem, locates, permits, bonds, subs, anything not material, labor or equipment.
A17: Summary | B17: Enter tax, overhead, contingency and profit rates on the Meta sheet. Summary reads them. Checks below the price show what is still blank; a blank is #N/A, never zero.
A19: Colors | B19: Blue fill = code writes here. Yellow fill with blue text = you type here. Green text = pulled from another sheet. Black = formula. Grey italic = reference only.
A20: Blue fill sample: | B20: Once filled, this workbook holds your real rates. Keep it out of the public repo, hosted APIs and Evolus Libraries.
A21: Yellow fill sample:
A22: Meta | B22: ratebook_id, version, effective_date, alternate_id and the four markup rates. Bump version on any rate change.
A23: Rate sources | B23: Every rate in this reference book is a fictional estimate for demonstration. No vendor quote, listing, place or published wage figure is behind it.

Sheet Meta
A1: key | B1: value | C1: notes
A2: ratebook_id | B2: IFI-REF-FICTIONAL | C2: Stable identifier for this company's rate book.
A3: version | B3: 2.3.0 | C3: Semantic version. Bump on ANY rate change; approvals bind to it.
A4: effective_date | B4: 46307 | C4: Date these rates take effect (ISO). Later than today = rejected.
A5: currency | B5: USD | C5: Only USD is supported.
A6: alternate_id | B6: ALT-A1 | C6: Scope id that the *_alt columns price.
A7: data_classification | B7: FICTIONAL_DEMO | C7: FICTIONAL_DEMO or COMPANY_PRIVATE. Private books never enter Git.
A8: tax_materials_pct | B8: 0.07 | C8: Sales tax on materials.
A9: overhead_pct | B9: 0.1 | C9: Overhead on direct cost.
A10: contingency_pct | B10: 0.05 | C10: Contingency on direct cost.
A11: profit_pct | B11: 0.1 | C11: Profit on direct + overhead + contingency.
A12: workday_hours | B12: 8 | C12: Productive hours in a crew workday: converts crew-hours to duration in days.

Sheet Takeoff_In
A1: key | B1: description | C1: uom | D1: qty_base | E1: qty_alt | F1: source_ref | G1: notes
A2: M01 | B2: Post, Type A terminal / corner / gate | 2-7/8 in OD (2.875), hot-dip galvanized steel pipe. Wall / weight class not specified. Stock length per Takeoff. | C2: EA
A3: M02 | B3: Post, Type A line | 2-3/8 in OD (2.375), hot-dip galvanized steel pipe. Wall / weight class not specified. Stock length per Takeoff. | C3: EA
A4: M03 | B4: Post, Type B terminal | 2-3/8 in OD (2.375), hot-dip galvanized steel pipe, stock length per Takeoff (Type B). | C4: EA
A5: M04 | B5: Post, Type B line | 1-7/8 in OD (nominal 1.900), hot-dip galvanized steel pipe, stock length per Takeoff (Type B). | C5: EA
A6: M05 | B6: Top rail | 1-5/8 in OD (1.660), galvanized, swaged, continuous. Type A + Type B. | C6: LF
A7: M06 | B7: Mid rail / brace rail, Type A | 1-5/8 in OD (1.660), galvanized, at 5'-0". Continuous per F501 elevation; brace rail at terminals is the mid rail. | C7: LF
A8: M07 | B8: Rail sleeve / coupling | For 1-5/8 in OD rail (swaged-end or expansion sleeve). | C8: EA
A9: M08 | B9: Truss rod with turnbuckle, fence braces | 3/8 in dia, galvanized, adjustable, to span a 10 ft bay at 5 ft height (about 11 ft 2 in diagonal). | C9: EA
A10: M09 | B10: Brace band, terminal-side | For 2-7/8 in OD post and 1-5/8 in OD rail / 3/8 in truss rod. | C10: EA
A11: M10 | B11: Brace band, line-post side | For 2-3/8 in OD post and 1-5/8 in OD rail / 3/8 in truss rod. | C11: EA
A12: M11 | B12: Rail end cup / rail end band | For 1-5/8 in OD rail at terminal, corner and gate posts. | C12: EA
A13: M12 | B13: Tension bar, Type A | 3/16 x 3/4 in flat bar, galvanized, about 118 in long (10 ft fabric). | C13: EA
... A57: D12 | B57: Layout / stakeout length (gross perimeter + dividers) | C57: LF

Sheet Materials
A1: item_id | B1: category | C1: item | D1: spec | E1: uom | F1: unit_price | G1: vendor | H1: price_date | I1: source_url_or_sku | J1: overage_pct | K1: qty_base | L1: qty_alt | M1: order_qty_base | N1: order_qty_alt | O1: ext_base | P1: ext_alt | Q1: notes
A2: M01 | B2: Framework | C2: Post, Type A terminal / corner / gate | D2: 2-7/8 in OD (2.875), hot-dip galvanized steel pipe. Wall / weight class not specified. Stock length per Takeoff. | E2: EA | F2: 98 | G2: Reference estimate | H2: 46307 | I2: reference estimate | J2: 0 | K2: =IF($A2="","",IF(INDEX(Takeoff_In!$D$2:$D$300,MATCH($A2,Takeoff_In!$A$2:$A$300,0))="",NA(),INDEX(Takeoff_In!$D$2:$D$300,MATCH($A2,Takeoff_In!$A$2:$A$300,0)))) | L2: =IF($A2="","",IF(INDEX(Takeoff_In!$E$2:$E$300,MATCH($A2,Takeoff_In!$A$2:$A$300,0))="",NA(),INDEX(Takeoff_In!$E$2:$E$300,MATCH($A2,Takeoff_In!$A$2:$A$300,0)))) | M2: =IF($A2="","",IF(ISNUMBER($J2),IF($E2="CU YD",ROUNDUP(K2*(1+$J2),1),ROUNDUP(K2*(1+$J2),0)),NA())) | N2: =IF($A2="","",IF(ISNUMBER($J2),IF($E2="CU YD",ROUNDUP(L2*(1+$J2),1),ROUNDUP(L2*(1+$J2),0)),NA())) | O2: =IF($A2="","",IF(ISNUMBER($F2),M2*$F2,NA())) | P2: =IF($A2="","",IF(ISNUMBER($F2),N2*$F2,NA())) | Q2: Fictional reference estimate; not a vendor quote.
A3: M02 | B3: Framework | C3: Post, Type A line | D3: 2-3/8 in OD (2.375), hot-dip galvanized steel pipe. Wall / weight class not specified. Stock length per Takeoff. | E3: EA | F3: 68 | G3: Reference estimate | H3: 46307 | I3: reference estimate | J3: 0 | K3: =IF($A3="","",IF(INDEX(Takeoff_In!$D$2:$D$300,MATCH($A3,Takeoff_In!$A$2:$A$300,0))="",NA(),INDEX(Takeoff_In!$D$2:$D$300,MATCH($A3,Takeoff_In!$A$2:$A$300,0)))) | L3: =IF($A3="","",IF(INDEX(Takeoff_In!$E$2:$E$300,MATCH($A3,Takeoff_In!$A$2:$A$300,0))="",NA(),INDEX(Takeoff_In!$E$2:$E$300,MATCH($A3,Takeoff_In!$A$2:$A$300,0)))) | M3: =IF($A3="","",IF(ISNUMBER($J3),IF($E3="CU YD",ROUNDUP(K3*(1+$J3),1),ROUNDUP(K3*(1+$J3),0)),NA())) | N3: =IF($A3="","",IF(ISNUMBER($J3),IF($E3="CU YD",ROUNDUP(L3*(1+$J3),1),ROUNDUP(L3*(1+$J3),0)),NA())) | O3: =IF($A3="","",IF(ISNUMBER($F3),M3*$F3,NA())) | P3: =IF($A3="","",IF(ISNUMBER($F3),N3*$F3,NA())) | Q3: Fictional reference estimate; not a vendor quote.
A4: M03 | B4: Framework | C4: Post, Type B terminal | D4: 2-3/8 in OD (2.375), hot-dip galvanized steel pipe, stock length per Takeoff (Type B). | E4: EA | F4: 30 | G4: Reference estimate | H4: 46307 | I4: reference estimate | J4: 0 | K4: =IF($A4="","",IF(INDEX(Takeoff_In!$D$2:$D$300,MATCH($A4,Takeoff_In!$A$2:$A$300,0))="",NA(),INDEX(Takeoff_In!$D$2:$D$300,MATCH($A4,Takeoff_In!$A$2:$A$300,0)))) | L4: =IF($A4="","",IF(INDEX(Takeoff_In!$E$2:$E$300,MATCH($A4,Takeoff_In!$A$2:$A$300,0))="",NA(),INDEX(Takeoff_In!$E$2:$E$300,MATCH($A4,Takeoff_In!$A$2:$A$300,0)))) | M4: =IF($A4="","",IF(ISNUMBER($J4),IF($E4="CU YD",ROUNDUP(K4*(1+$J4),1),ROUNDUP(K4*(1+$J4),0)),NA())) | N4: =IF($A4="","",IF(ISNUMBER($J4),IF($E4="CU YD",ROUNDUP(L4*(1+$J4),1),ROUNDUP(L4*(1+$J4),0)),NA())) | O4: =IF($A4="","",IF(ISNUMBER($F4),M4*$F4,NA())) | P4: =IF($A4="","",IF(ISNUMBER($F4),N4*$F4,NA())) | Q4: Fictional reference estimate; not a vendor quote.
A5: M04 | B5: Framework | C5: Post, Type B line | D5: 1-7/8 in OD (nominal 1.900), hot-dip galvanized steel pipe, stock length per Takeoff (Type B). | E5: EA | F5: 24 | G5: Reference estimate | H5: 46307 | I5: reference estimate | J5: 0 | K5: =IF($A5="","",IF(INDEX(Takeoff_In!$D$2:$D$300,MATCH($A5,Takeoff_In!$A$2:$A$300,0))="",NA(),INDEX(Takeoff_In!$D$2:$D$300,MATCH($A5,Takeoff_In!$A$2:$A$300,0)))) | L5: =IF($A5="","",IF(INDEX(Takeoff_In!$E$2:$E$300,MATCH($A5,Takeoff_In!$A$2:$A$300,0))="",NA(),INDEX(Takeoff_In!$E$2:$E$300,MATCH($A5,Takeoff_In!$A$2:$A$300,0)))) | M5: =IF($A5="","",IF(ISNUMBER($J5),IF($E5="CU YD",ROUNDUP(K5*(1+$J5),1),ROUNDUP(K5*(1+$J5),0)),NA())) | N5: =IF($A5="","",IF(ISNUMBER($J5),IF($E5="CU YD",ROUNDUP(L5*(1+$J5),1),ROUNDUP(L5*(1+$J5),0)),NA())) | O5: =IF($A5="","",IF(ISNUMBER($F5),M5*$F5,NA())) | P5: =IF($A5="","",IF(ISNUMBER($F5),N5*$F5,NA())) | Q5: Fictional reference estimate; not a vendor quote.
A6: M05 | B6: Framework | C6: Top rail | D6: 1-5/8 in OD (1.660), galvanized, swaged, continuous. Type A + Type B. | E6: LF | F6: 1.9 | G6: Reference estimate | H6: 46307 | J6: 0.05 | K6: =IF($A6="","",IF(INDEX(Takeoff_In!$D$2:$D$300,MATCH($A6,Takeoff_In!$A$2:$A$300,0))="",NA(),INDEX(Takeoff_In!$D$2:$D$300,MATCH($A6,Takeoff_In!$A$2:$A$300,0)))) | L6: =IF($A6="","",IF(INDEX(Takeoff_In!$E$2:$E$300,MATCH($A6,Takeoff_In!$A$2:$A$300,0))="",NA(),INDEX(Takeoff_In!$E$2:$E$300,MATCH($A6,Takeoff_In!$A$2:$A$300,0)))) | M6: =IF($A6="","",IF(ISNUMBER($J6),IF($E6="CU YD",ROUNDUP(K6*(1+$J6),1),ROUNDUP(K6*(1+$J6),0)),NA())) | N6: =IF($A6="","",IF(ISNUMBER($J6),IF($E6="CU YD",ROUNDUP(L6*(1+$J6),1),ROUNDUP(L6*(1+$J6),0)),NA())) | O6: =IF($A6="","",IF(ISNUMBER($F6),M6*$F6,NA())) | P6: =IF($A6="","",IF(ISNUMBER($F6),N6*$F6,NA())) | Q6: Per LF of 1-5/8 rail. Estimate.
A7: M06 | B7: Framework | C7: Mid rail / brace rail, Type A | D7: 1-5/8 in OD (1.660), galvanized, at 5'-0". Continuous per F501 elevation; brace rail at terminals is the mid rail. | E7: LF | F7: 1.9 | G7: Reference estimate | H7: 46307 | J7: 0.05 | K7: =IF($A7="","",IF(INDEX(Takeoff_In!$D$2:$D$300,MATCH($A7,Takeoff_In!$A$2:$A$300,0))="",NA(),INDEX(Takeoff_In!$D$2:$D$300,MATCH($A7,Takeoff_In!$A$2:$A$300,0)))) | L7: =IF($A7="","",IF(INDEX(Takeoff_In!$E$2:$E$300,MATCH($A7,Takeoff_In!$A$2:$A$300,0))="",NA(),INDEX(Takeoff_In!$E$2:$E$300,MATCH($A7,Takeoff_In!$A$2:$A$300,0)))) | M7: =IF($A7="","",IF(ISNUMBER($J7),IF($E7="CU YD",ROUNDUP(K7*(1+$J7),1),ROUNDUP(K7*(1+$J7),0)),NA())) | N7: =IF($A7="","",IF(ISNUMBER($J7),IF($E7="CU YD",ROUNDUP(L7*(1+$J7),1),ROUNDUP(L7*(1+$J7),0)),NA())) | O7: =IF($A7="","",IF(ISNUMBER($F7),M7*$F7,NA())) | P7: =IF($A7="","",IF(ISNUMBER($F7),N7*$F7,NA())) | Q7: Same rail as M05.
A8: M07 | B8: Framework | C8: Rail sleeve / coupling | D8: For 1-5/8 in OD rail (swaged-end or expansion sleeve). | E8: EA | F8: 3.5 | G8: Reference estimate | H8: 46307 | J8: 0.1 | K8: =IF($A8="","",IF(INDEX(Takeoff_In!$D$2:$D$300,MATCH($A8,Takeoff_In!$A$2:$A$300,0))="",NA(),INDEX(Takeoff_In!$D$2:$D$300,MATCH($A8,Takeoff_In!$A$2:$A$300,0)))) | L8: =IF($A8="","",IF(INDEX(Takeoff_In!$E$2:$E$300,MATCH($A8,Takeoff_In!$A$2:$A$300,0))="",NA(),INDEX(Takeoff_In!$E$2:$E$300,MATCH($A8,Takeoff_In!$A$2:$A$300,0)))) | M8: =IF($A8="","",IF(ISNUMBER($J8),IF($E8="CU YD",ROUNDUP(K8*(1+$J8),1),ROUNDUP(K8*(1+$J8),0)),NA())) | N8: =IF($A8="","",IF(ISNUMBER($J8),IF($E8="CU YD",ROUNDUP(L8*(1+$J8),1),ROUNDUP(L8*(1+$J8),0)),NA())) | O8: =IF($A8="","",IF(ISNUMBER($F8),M8*$F8,NA())) | P8: =IF($A8="","",IF(ISNUMBER($F8),N8*$F8,NA()))
A9: M08 | B9: Framework | C9: Truss rod with turnbuckle, fence braces | D9: 3/8 in dia, galvanized, adjustable, to span a 10 ft bay at 5 ft height (about 11 ft 2 in diagonal). | E9: EA | F9: 14 | G9: Reference estimate | H9: 46307 | J9: 0.1 | K9: =IF($A9="","",IF(INDEX(Takeoff_In!$D$2:$D$300,MATCH($A9,Takeoff_In!$A$2:$A$300,0))="",NA(),INDEX(Takeoff_In!$D$2:$D$300,MATCH($A9,Takeoff_In!$A$2:$A$300,0)))) | L9: =IF($A9="","",IF(INDEX(Takeoff_In!$E$2:$E$300,MATCH($A9,Takeoff_In!$A$2:$A$300,0))="",NA(),INDEX(Takeoff_In!$E$2:$E$300,MATCH($A9,Takeoff_In!$A$2:$A$300,0)))) | M9: =IF($A9="","",IF(ISNUMBER($J9),IF($E9="CU YD",ROUNDUP(K9*(1+$J9),1),ROUNDUP(K9*(1+$J9),0)),NA())) | N9: =IF($A9="","",IF(ISNUMBER($J9),IF($E9="CU YD",ROUNDUP(L9*(1+$J9),1),ROUNDUP(L9*(1+$J9),0)),NA())) | O9: =IF($A9="","",IF(ISNUMBER($F9),M9*$F9,NA())) | P9: =IF($A9="","",IF(ISNUMBER($F9),N9*$F9,NA())) | Q9: 3/8 truss rod with turnbuckle, about 11 ft.
A10: M09 | B10: Framework | C10: Brace band, terminal-side | D10: For 2-7/8 in OD post and 1-5/8 in OD rail / 3/8 in truss rod. | E10: EA | F10: 3.25 | G10: Reference estimate | H10: 46307 | J10: 0.1 | K10: =IF($A10="","",IF(INDEX(Takeoff_In!$D$2:$D$300,MATCH($A10,Takeoff_In!$A$2:$A$300,0))="",NA(),INDEX(Takeoff_In!$D$2:$D$300,MATCH($A10,Takeoff_In!$A$2:$A$300,0)))) | L10: =IF($A10="","",IF(INDEX(Takeoff_In!$E$2:$E$300,MATCH($A10,Takeoff_In!$A$2:$A$300,0))="",NA(),INDEX(Takeoff_In!$E$2:$E$300,MATCH($A10,Takeoff_In!$A$2:$A$300,0)))) | M10: =IF($A10="","",IF(ISNUMBER($J10),IF($E10="CU YD",ROUNDUP(K10*(1+$J10),1),ROUNDUP(K10*(1+$J10),0)),NA())) | N10: =IF($A10="","",IF(ISNUMBER($J10),IF($E10="CU YD",ROUNDUP(L10*(1+$J10),1),ROUNDUP(L10*(1+$J10),0)),NA())) | O10: =IF($A10="","",IF(ISNUMBER($F10),M10*$F10,NA())) | P10: =IF($A10="","",IF(ISNUMBER($F10),N10*$F10,NA()))
A11: M10 | B11: Framework | C11: Brace band, line-post side | D11: For 2-3/8 in OD post and 1-5/8 in OD rail / 3/8 in truss rod. | E11: EA | F11: 3 | G11: Reference estimate | H11: 46307 | J11: 0.1 | K11: =IF($A11="","",IF(INDEX(Takeoff_In!$D$2:$D$300,MATCH($A11,Takeoff_In!$A$2:$A$300,0))="",NA(),INDEX(Takeoff_In!$D$2:$D$300,MATCH($A11,Takeoff_In!$A$2:$A$300,0)))) | L11: =IF($A11="","",IF(INDEX(Takeoff_In!$E$2:$E$300,MATCH($A11,Takeoff_In!$A$2:$A$300,0))="",NA(),INDEX(Takeoff_In!$E$2:$E$300,MATCH($A11,Takeoff_In!$A$2:$A$300,0)))) | M11: =IF($A11="","",IF(ISNUMBER($J11),IF($E11="CU YD",ROUNDUP(K11*(1+$J11),1),ROUNDUP(K11*(1+$J11),0)),NA())) | N11: =IF($A11="","",IF(ISNUMBER($J11),IF($E11="CU YD",ROUNDUP(L11*(1+$J11),1),ROUNDUP(L11*(1+$J11),0)),NA())) | O11: =IF($A11="","",IF(ISNUMBER($F11),M11*$F11,NA())) | P11: =IF($A11="","",IF(ISNUMBER($F11),N11*$F11,NA()))
A12: M11 | B12: Framework | C12: Rail end cup / rail end band | D12: For 1-5/8 in OD rail at terminal, corner and gate posts. | E12: EA | F12: 2.25 | G12: Reference estimate | H12: 46307 | J12: 0.1 | K12: =IF($A12="","",IF(INDEX(Takeoff_In!$D$2:$D$300,MATCH($A12,Takeoff_In!$A$2:$A$300,0))="",NA(),INDEX(Takeoff_In!$D$2:$D$300,MATCH($A12,Takeoff_In!$A$2:$A$300,0)))) | L12: =IF($A12="","",IF(INDEX(Takeoff_In!$E$2:$E$300,MATCH($A12,Takeoff_In!$A$2:$A$300,0))="",NA(),INDEX(Takeoff_In!$E$2:$E$300,MATCH($A12,Takeoff_In!$A$2:$A$300,0)))) | M12: =IF($A12="","",IF(ISNUMBER($J12),IF($E12="CU YD",ROUNDUP(K12*(1+$J12),1),ROUNDUP(K12*(1+$J12),0)),NA())) | N12: =IF($A12="","",IF(ISNUMBER($J12),IF($E12="CU YD",ROUNDUP(L12*(1+$J12),1),ROUNDUP(L12*(1+$J12),0)),NA())) | O12: =IF($A12="","",IF(ISNUMBER($F12),M12*$F12,NA())) | P12: =IF($A12="","",IF(ISNUMBER($F12),N12*$F12,NA()))
A13: M12 | B13: Fabric hardware | C13: Tension bar, Type A | D13: 3/16 x 3/4 in flat bar, galvanized, about 118 in long (10 ft fabric). | E13: EA | F13: 9.5 | G13: Reference estimate | H13: 46307 | J13: 0.1 | K13: =IF($A13="","",IF(INDEX(Takeoff_In!$D$2:$D$300,MATCH($A13,Takeoff_In!$A$2:$A$300,0))="",NA(),INDEX(Takeoff_In!$D$2:$D$300,MATCH($A13,Takeoff_In!$A$2:$A$300,0)))) | L13: =IF($A13="","",IF(INDEX(Takeoff_In!$E$2:$E$300,MATCH($A13,Takeoff_In!$A$2:$A$300,0))="",NA(),INDEX(Takeoff_In!$E$2:$E$300,MATCH($A13,Takeoff_In!$A$2:$A$300,0)))) | M13: =IF($A13="","",IF(ISNUMBER($J13),IF($E13="CU YD",ROUNDUP(K13*(1+$J13),1),ROUNDUP(K13*(1+$J13),0)),NA())) | N13: =IF($A13="","",IF(ISNUMBER($J13),IF($E13="CU YD",ROUNDUP(L13*(1+$J13),1),ROUNDUP(L13*(1+$J13),0)),NA())) | O13: =IF($A13="","",IF(ISNUMBER($F13),M13*$F13,NA())) | P13: =IF($A13="","",IF(ISNUMBER($F13),N13*$F13,NA())) | Q13: 118 in bar.
A14: M13 | B14: Fabric hardware | C14: Tension bar, Type B | D14: 3/16 x 3/4 in flat bar, galvanized, about 40 in long (42 in fabric). | E14: EA | F14: 3.6 | G14: Reference estimate | H14: 46307 | J14: 0.1 | K14: =IF($A14="","",IF(INDEX(Takeoff_In!$D$2:$D$300,MATCH($A14,Takeoff_In!$A$2:$A$300,0))="",NA(),INDEX(Takeoff_In!$D$2:$D$300,MATCH($A14,Takeoff_In!$A$2:$A$300,0)))) | L14: =IF($A14="","",IF(INDEX(Takeoff_In!$E$2:$E$300,MATCH($A14,Takeoff_In!$A$2:$A$300,0))="",NA(),INDEX(Takeoff_In!$E$2:$E$300,MATCH($A14,Takeoff_In!$A$2:$A$300,0)))) | M14: =IF($A14="","",IF(ISNUMBER($J14),IF($E14="CU YD",ROUNDUP(K14*(1+$J14),1),ROUNDUP(K14*(1+$J14),0)),NA())) | N14: =IF($A14="","",IF(ISNUMBER($J14),IF($E14="CU YD",ROUNDUP(L14*(1+$J14),1),ROUNDUP(L14*(1+$J14),0)),NA())) | O14: =IF($A14="","",IF(ISNUMBER($F14),M14*$F14,NA())) | P14: =IF($A14="","",IF(ISNUMBER($F14),N14*$F14,NA())) | Q14: 40 in bar.
A15: M14 | B15: Fabric hardware | C15: Tension band, 2-7/8 in post | D15: For 3/4 in tension bar on 2-7/8 in OD post. | E15: EA | F15: 1.6 | G15: Reference estimate | H15: 46307 | J15: 0.1 | K15: =IF($A15="","",IF(INDEX(Takeoff_In!$D$2:$D$300,MATCH($A15,Takeoff_In!$A$2:$A$300,0))="",NA(),INDEX(Takeoff_In!$D$2:$D$300,MATCH($A15,Takeoff_In!$A$2:$A$300,0)))) | L15: =IF($A15="","",IF(INDEX(Takeoff_In!$E$2:$E$300,MATCH($A15,Takeoff_In!$A$2:$A$300,0))="",NA(),INDEX(Takeoff_In!$E$2:$E$300,MATCH($A15,Takeoff_In!$A$2:$A$300,0)))) | M15: =IF($A15="","",IF(ISNUMBER($J15),IF($E15="CU YD",ROUNDUP(K15*(1+$J15),1),ROUNDUP(K15*(1+$J15),0)),NA())) | N15: =IF($A15="","",IF(ISNUMBER($J15),IF($E15="CU YD",ROUNDUP(L15*(1+$J15),1),ROUNDUP(L15*(1+$J15),0)),NA())) | O15: =IF($A15="","",IF(ISNUMBER($F15),M15*$F15,NA())) | P15: =IF($A15="","",IF(ISNUMBER($F15),N15*$F15,NA()))
A16: M15 | B16: Fabric hardware | C16: Tension band, 2-3/8 in post | D16: For 3/4 in tension bar on 2-3/8 in OD post (Type B terminals). | E16: EA | F16: 1.4 | G16: Reference estimate | H16: 46307 | J16: 0.1 | K16: =IF($A16="","",IF(INDEX(Takeoff_In!$D$2:$D$300,MATCH($A16,Takeoff_In!$A$2:$A$300,0))="",NA(),INDEX(Takeoff_In!$D$2:$D$300,MATCH($A16,Takeoff_In!$A$2:$A$300,0)))) | L16: =IF($A16="","",IF(INDEX(Takeoff_In!$E$2:$E$300,MATCH($A16,Takeoff_In!$A$2:$A$300,0))="",NA(),INDEX(Takeoff_In!$E$2:$E$300,MATCH($A16,Takeoff_In!$A$2:$A$300,0)))) | M16: =IF($A16="","",IF(ISNUMBER($J16),IF($E16="CU YD",ROUNDUP(K16*(1+$J16),1),ROUNDUP(K16*(1+$J16),0)),NA())) | N16: =IF($A16="","",IF(ISNUMBER($J16),IF($E16="CU YD",ROUNDUP(L16*(1+$J16),1),ROUNDUP(L16*(1+$J16),0)),NA())) | O16: =IF($A16="","",IF(ISNUMBER($F16),M16*$F16,NA())) | P16: =IF($A16="","",IF(ISNUMBER($F16),N16*$F16,NA()))
A17: M16 | B17: Framework | C17: Post cap, 2-7/8 in | D17: Galvanized, for 2-7/8 in OD post. Dome vs loop-top not stated ('POST CAP, TYP.'). | E17: EA | F17: 4.75 | G17: Reference estimate | H17: 46307 | J17: 0.1 | K17: =IF($A17="","",IF(INDEX(Takeoff_In!$D$2:$D$300,MATCH($A17,Takeoff_In!$A$2:$A$300,0))="",NA(),INDEX(Takeoff_In!$D$2:$D$300,MATCH($A17,Takeoff_In!$A$2:$A$300,0)))) | L17: =IF($A17="","",IF(INDEX(Takeoff_In!$E$2:$E$300,MATCH($A17,Takeoff_In!$A$2:$A$300,0))="",NA(),INDEX(Takeoff_In!$E$2:$E$300,MATCH($A17,Takeoff_In!$A$2:$A$300,0)))) | M17: =IF($A17="","",IF(ISNUMBER($J17),IF($E17="CU YD",ROUNDUP(K17*(1+$J17),1),ROUNDUP(K17*(1+$J17),0)),NA())) | N17: =IF($A17="","",IF(ISNUMBER($J17),IF($E17="CU YD",ROUNDUP(L17*(1+$J17),1),ROUNDUP(L17*(1+$J17),0)),NA())) | O17: =IF($A17="","",IF(ISNUMBER($F17),M17*$F17,NA())) | P17: =IF($A17="","",IF(ISNUMBER($F17),N17*$F17,NA()))
A18: M17 | B18: Framework | C18: Post cap, 2-3/8 in | D18: Galvanized, for 2-3/8 in OD post (Type A line posts and Type B terminals). Dome vs loop-top not stated. | E18: EA | F18: 3.5 | G18: Reference estimate | H18: 46307 | J18: 0.1 | K18: =IF($A18="","",IF(INDEX(Takeoff_In!$D$2:$D$300,MATCH($A18,Takeoff_In!$A$2:$A$300,0))="",NA(),INDEX(Takeoff_In!$D$2:$D$300,MATCH($A18,Takeoff_In!$A$2:$A$300,0)))) | L18: =IF($A18="","",IF(INDEX(Takeoff_In!$E$2:$E$300,MATCH($A18,Takeoff_In!$A$2:$A$300,0))="",NA(),INDEX(Takeoff_In!$E$2:$E$300,MATCH($A18,Takeoff_In!$A$2:$A$300,0)))) | M18: =IF($A18="","",IF(ISNUMBER($J18),IF($E18="CU YD",ROUNDUP(K18*(1+$J18),1),ROUNDUP(K18*(1+$J18),0)),NA())) | N18: =IF($A18="","",IF(ISNUMBER($J18),IF($E18="CU YD",ROUNDUP(L18*(1+$J18),1),ROUNDUP(L18*(1+$J18),0)),NA())) | O18: =IF($A18="","",IF(ISNUMBER($F18),M18*$F18,NA())) | P18: =IF($A18="","",IF(ISNUMBER($F18),N18*$F18,NA()))
A19: M18 | B19: Framework | C19: Post cap, 1-7/8 in | D19: Galvanized, for 1-7/8 in OD post (Type B line posts). | E19: EA | F19: 2.75 | G19: Reference estimate | H19: 46307 | J19: 0.1 | K19: =IF($A19="","",IF(INDEX(Takeoff_In!$D$2:$D$300,MATCH($A19,Takeoff_In!$A$2:$A$300,0))="",NA(),INDEX(Takeoff_In!$D$2:$D$300,MATCH($A19,Takeoff_In!$A$2:$A$300,0)))) | L19: =IF($A19="","",IF(INDEX(Takeoff_In!$E$2:$E$300,MATCH($A19,Takeoff_In!$A$2:$A$300,0))="",NA(),INDEX(Takeoff_In!$E$2:$E$300,MATCH($A19,Takeoff_In!$A$2:$A$300,0)))) | M19: =IF($A19="","",IF(ISNUMBER($J19),IF($E19="CU YD",ROUNDUP(K19*(1+$J19),1),ROUNDUP(K19*(1+$J19),0)),NA())) | N19: =IF($A19="","",IF(ISNUMBER($J19),IF($E19="CU YD",ROUNDUP(L19*(1+$J19),1),ROUNDUP(L19*(1+$J19),0)),NA())) | O19: =IF($A19="","",IF(ISNUMBER($F19),M19*$F19,NA())) | P19: =IF($A19="","",IF(ISNUMBER($F19),N19*$F19,NA()))
A20: M19 | B20: Fabric | C20: Chain link fabric, 10 ft | D20: 120 in high, 9 ga core, 2 in mesh, galvanized, KK/KK selvages. Coating class not specified. | E20: LF | F20: 12.5 | G20: Reference estimate | H20: 46307 | I20: reference estimate | J20: 0.05 | K20: =IF($A20="","",IF(INDEX(Takeoff_In!$D$2:$D$300,MATCH($A20,Takeoff_In!$A$2:$A$300,0))="",NA(),INDEX(Takeoff_In!$D$2:$D$300,MATCH($A20,Takeoff_In!$A$2:$A$300,0)))) | L20: =IF($A20="","",IF(INDEX(Takeoff_In!$E$2:$E$300,MATCH($A20,Takeoff_In!$A$2:$A$300,0))="",NA(),INDEX(Takeoff_In!$E$2:$E$300,MATCH($A20,Takeoff_In!$A$2:$A$300,0)))) | M20: =IF($A20="","",IF(ISNUMBER($J20),IF($E20="CU YD",ROUNDUP(K20*(1+$J20),1),ROUNDUP(K20*(1+$J20),0)),NA())) | N20: =IF($A20="","",IF(ISNUMBER($J20),IF($E20="CU YD",ROUNDUP(L20*(1+$J20),1),ROUNDUP(L20*(1+$J20),0)),NA())) | O20: =IF($A20="","",IF(ISNUMBER($F20),M20*$F20,NA())) | P20: =IF($A20="","",IF(ISNUMBER($F20),N20*$F20,NA())) | Q20: Fictional reference estimate; not a vendor quote.
A21: M20 | B21: Fabric | C21: Chain link fabric, 42 in | D21: 42 in high, 9 ga core, 2 in mesh, galvanized, KK/KK selvages. | E21: LF | F21: 4.75 | G21: Reference estimate | H21: 46307 | I21: reference estimate | J21: 0.05 | K21: =IF($A21="","",IF(INDEX(Takeoff_In!$D$2:$D$300,MATCH($A21,Takeoff_In!$A$2:$A$300,0))="",NA(),INDEX(Takeoff_In!$D$2:$D$300,MATCH($A21,Takeoff_In!$A$2:$A$300,0)))) | L21: =IF($A21="","",IF(INDEX(Takeoff_In!$E$2:$E$300,MATCH($A21,Takeoff_In!$A$2:$A$300,0))="",NA(),INDEX(Takeoff_In!$E$2:$E$300,MATCH($A21,Takeoff_In!$A$2:$A$300,0)))) | M21: =IF($A21="","",IF(ISNUMBER($J21),IF($E21="CU YD",ROUNDUP(K21*(1+$J21),1),ROUNDUP(K21*(1+$J21),0)),NA())) | N21: =IF($A21="","",IF(ISNUMBER($J21),IF($E21="CU YD",ROUNDUP(L21*(1+$J21),1),ROUNDUP(L21*(1+$J21),0)),NA())) | O21: =IF($A21="","",IF(ISNUMBER($F21),M21*$F21,NA())) | P21: =IF($A21="","",IF(ISNUMBER($F21),N21*$F21,NA())) | Q21: Fictional reference estimate; not a vendor quote.
A22: M21 | B22: Fabric | C22: Gate leaf fabric | D22: 84 in high (7 ft frame), 9 ga core, 2 in mesh, galvanized. Matches fence fabric. | E22: LF | F22: 8.75 | G22: Reference estimate | H22: 46307 | I22: reference estimate | J22: 0.05 | K22: =IF($A22="","",IF(INDEX(Takeoff_In!$D$2:$D$300,MATCH($A22,Takeoff_In!$A$2:$A$300,0))="",NA(),INDEX(Takeoff_In!$D$2:$D$300,MATCH($A22,Takeoff_In!$A$2:$A$300,0)))) | L22: =IF($A22="","",IF(INDEX(Takeoff_In!$E$2:$E$300,MATCH($A22,Takeoff_In!$A$2:$A$300,0))="",NA(),INDEX(Takeoff_In!$E$2:$E$300,MATCH($A22,Takeoff_In!$A$2:$A$300,0)))) | M22: =IF($A22="","",IF(ISNUMBER($J22),IF($E22="CU YD",ROUNDUP(K22*(1+$J22),1),ROUNDUP(K22*(1+$J22),0)),NA())) | N22: =IF($A22="","",IF(ISNUMBER($J22),IF($E22="CU YD",ROUNDUP(L22*(1+$J22),1),ROUNDUP(L22*(1+$J22),0)),NA())) | O22: =IF($A22="","",IF(ISNUMBER($F22),M22*$F22,NA())) | P22: =IF($A22="","",IF(ISNUMBER($F22),N22*$F22,NA())) | Q22: 84 in, scaled.
A23: M22 | B23: Fabric | C23: Transom fabric above gate header | D23: 36 in high, 9 ga core, 2 in mesh, galvanized (10 ft fence minus 7 ft gate). | E23: LF | F23: 4 | G23: Reference estimate | H23: 46307 | I23: reference estimate | J23: 0.05 | K23: =IF($A23="","",IF(INDEX(Takeoff_In!$D$2:$D$300,MATCH($A23,Takeoff_In!$A$2:$A$300,0))="",NA(),INDEX(Takeoff_In!$D$2:$D$300,MATCH($A23,Takeoff_In!$A$2:$A$300,0)))) | L23: =IF($A23="","",IF(INDEX(Takeoff_In!$E$2:$E$300,MATCH($A23,Takeoff_In!$A$2:$A$300,0))="",NA(),INDEX(Takeoff_In!$E$2:$E$300,MATCH($A23,Takeoff_In!$A$2:$A$300,0)))) | M23: =IF($A23="","",IF(ISNUMBER($J23),IF($E23="CU YD",ROUNDUP(K23*(1+$J23),1),ROUNDUP(K23*(1+$J23),0)),NA())) | N23: =IF($A23="","",IF(ISNUMBER($J23),IF($E23="CU YD",ROUNDUP(L23*(1+$J23),1),ROUNDUP(L23*(1+$J23),0)),NA())) | O23: =IF($A23="","",IF(ISNUMBER($F23),M23*$F23,NA())) | P23: =IF($A23="","",IF(ISNUMBER($F23),N23*$F23,NA())) | Q23: 36 in, scaled.
A24: M23 | B24: Fabric | C24: Bottom tension wire | D24: 7 ga, galvanized, coil spring. Type A + Type B. | E24: LF | F24: 0.25 | G24: Reference estimate | H24: 46307 | J24: 0.05 | K24: =IF($A24="","",IF(INDEX(Takeoff_In!$D$2:$D$300,MATCH($A24,Takeoff_In!$A$2:$A$300,0))="",NA(),INDEX(Takeoff_In!$D$2:$D$300,MATCH($A24,Takeoff_In!$A$2:$A$300,0)))) | L24: =IF($A24="","",IF(INDEX(Takeoff_In!$E$2:$E$300,MATCH($A24,Takeoff_In!$A$2:$A$300,0))="",NA(),INDEX(Takeoff_In!$E$2:$E$300,MATCH($A24,Takeoff_In!$A$2:$A$300,0)))) | M24: =IF($A24="","",IF(ISNUMBER($J24),IF($E24="CU YD",ROUNDUP(K24*(1+$J24),1),ROUNDUP(K24*(1+$J24),0)),NA())) | N24: =IF($A24="","",IF(ISNUMBER($J24),IF($E24="CU YD",ROUNDUP(L24*(1+$J24),1),ROUNDUP(L24*(1+$J24),0)),NA())) | O24: =IF($A24="","",IF(ISNUMBER($F24),M24*$F24,NA())) | P24: =IF($A24="","",IF(ISNUMBER($F24),N24*$F24,NA())) | Q24: 7 ga coil.
A25: M24 | B25: Fabric hardware | C25: Fabric tie, 2-3/8 in post (Type A line) | D25: 9 ga aluminum tie wire, pre-formed for 2-3/8 in OD post. | E25: EA | F25: 0.28 | G25: Reference estimate | H25: 46307 | J25: 0.1 | K25: =IF($A25="","",IF(INDEX(Takeoff_In!$D$2:$D$300,MATCH($A25,Takeoff_In!$A$2:$A$300,0))="",NA(),INDEX(Takeoff_In!$D$2:$D$300,MATCH($A25,Takeoff_In!$A$2:$A$300,0)))) | L25: =IF($A25="","",IF(INDEX(Takeoff_In!$E$2:$E$300,MATCH($A25,Takeoff_In!$A$2:$A$300,0))="",NA(),INDEX(Takeoff_In!$E$2:$E$300,MATCH($A25,Takeoff_In!$A$2:$A$300,0)))) | M25: =IF($A25="","",IF(ISNUMBER($J25),IF($E25="CU YD",ROUNDUP(K25*(1+$J25),1),ROUNDUP(K25*(1+$J25),0)),NA())) | N25: =IF($A25="","",IF(ISNUMBER($J25),IF($E25="CU YD",ROUNDUP(L25*(1+$J25),1),ROUNDUP(L25*(1+$J25),0)),NA())) | O25: =IF($A25="","",IF(ISNUMBER($F25),M25*$F25,NA())) | P25: =IF($A25="","",IF(ISNUMBER($F25),N25*$F25,NA()))
A26: M25 | B26: Fabric hardware | C26: Fabric tie, 1-7/8 in post (Type B line) | D26: 9 ga aluminum tie wire, pre-formed for 1-7/8 in OD post. | E26: EA | F26: 0.26 | G26: Reference estimate | H26: 46307 | J26: 0.1 | K26: =IF($A26="","",IF(INDEX(Takeoff_In!$D$2:$D$300,MATCH($A26,Takeoff_In!$A$2:$A$300,0))="",NA(),INDEX(Takeoff_In!$D$2:$D$300,MATCH($A26,Takeoff_In!$A$2:$A$300,0)))) | L26: =IF($A26="","",IF(INDEX(Takeoff_In!$E$2:$E$300,MATCH($A26,Takeoff_In!$A$2:$A$300,0))="",NA(),INDEX(Takeoff_In!$E$2:$E$300,MATCH($A26,Takeoff_In!$A$2:$A$300,0)))) | M26: =IF($A26="","",IF(ISNUMBER($J26),IF($E26="CU YD",ROUNDUP(K26*(1+$J26),1),ROUNDUP(K26*(1+$J26),0)),NA())) | N26: =IF($A26="","",IF(ISNUMBER($J26),IF($E26="CU YD",ROUNDUP(L26*(1+$J26),1),ROUNDUP(L26*(1+$J26),0)),NA())) | O26: =IF($A26="","",IF(ISNUMBER($F26),M26*$F26,NA())) | P26: =IF($A26="","",IF(ISNUMBER($F26),N26*$F26,NA()))
A27: M26 | B27: Fabric hardware | C27: Fabric tie, 1-5/8 in rail | D27: 9 ga aluminum tie wire, pre-formed for 1-5/8 in OD rail. | E27: EA | F27: 0.22 | G27: Reference estimate | H27: 46307 | J27: 0.1 | K27: =IF($A27="","",IF(INDEX(Takeoff_In!$D$2:$D$300,MATCH($A27,Takeoff_In!$A$2:$A$300,0))="",NA(),INDEX(Takeoff_In!$D$2:$D$300,MATCH($A27,Takeoff_In!$A$2:$A$300,0)))) | L27: =IF($A27="","",IF(INDEX(Takeoff_In!$E$2:$E$300,MATCH($A27,Takeoff_In!$A$2:$A$300,0))="",NA(),INDEX(Takeoff_In!$E$2:$E$300,MATCH($A27,Takeoff_In!$A$2:$A$300,0)))) | M27: =IF($A27="","",IF(ISNUMBER($J27),IF($E27="CU YD",ROUNDUP(K27*(1+$J27),1),ROUNDUP(K27*(1+$J27),0)),NA())) | N27: =IF($A27="","",IF(ISNUMBER($J27),IF($E27="CU YD",ROUNDUP(L27*(1+$J27),1),ROUNDUP(L27*(1+$J27),0)),NA())) | O27: =IF($A27="","",IF(ISNUMBER($F27),M27*$F27,NA())) | P27: =IF($A27="","",IF(ISNUMBER($F27),N27*$F27,NA()))
A28: M27 | B28: Fabric hardware | C28: Tension wire tie / hog ring | D28: 9 ga aluminum tie or hog ring for 7 ga tension wire. | E28: EA | F28: 0.07 | G28: Reference estimate | H28: 46307 | J28: 0.1 | K28: =IF($A28="","",IF(INDEX(Takeoff_In!$D$2:$D$300,MATCH($A28,Takeoff_In!$A$2:$A$300,0))="",NA(),INDEX(Takeoff_In!$D$2:$D$300,MATCH($A28,Takeoff_In!$A$2:$A$300,0)))) | L28: =IF($A28="","",IF(INDEX(Takeoff_In!$E$2:$E$300,MATCH($A28,Takeoff_In!$A$2:$A$300,0))="",NA(),INDEX(Takeoff_In!$E$2:$E$300,MATCH($A28,Takeoff_In!$A$2:$A$300,0)))) | M28: =IF($A28="","",IF(ISNUMBER($J28),IF($E28="CU YD",ROUNDUP(K28*(1+$J28),1),ROUNDUP(K28*(1+$J28),0)),NA())) | N28: =IF($A28="","",IF(ISNUMBER($J28),IF($E28="CU YD",ROUNDUP(L28*(1+$J28),1),ROUNDUP(L28*(1+$J28),0)),NA())) | O28: =IF($A28="","",IF(ISNUMBER($F28),M28*$F28,NA())) | P28: =IF($A28="","",IF(ISNUMBER($F28),N28*$F28,NA()))
A29: M28 | B29: Gates | C29: Gate frame pipe | D29: 1-7/8 in OD (nominal 1.900), galvanized. Leaf = 2 verticals + 3 horizontals. | E29: LF | F29: 3.2 | G29: Reference estimate | H29: 46307 | J29: 0 | K29: =IF($A29="","",IF(INDEX(Takeoff_In!$D$2:$D$300,MATCH($A29,Takeoff_In!$A$2:$A$300,0))="",NA(),INDEX(Takeoff_In!$D$2:$D$300,MATCH($A29,Takeoff_In!$A$2:$A$300,0)))) | L29: =IF($A29="","",IF(INDEX(Takeoff_In!$E$2:$E$300,MATCH($A29,Takeoff_In!$A$2:$A$300,0))="",NA(),INDEX(Takeoff_In!$E$2:$E$300,MATCH($A29,Takeoff_In!$A$2:$A$300,0)))) | M29: =IF($A29="","",IF(ISNUMBER($J29),IF($E29="CU YD",ROUNDUP(K29*(1+$J29),1),ROUNDUP(K29*(1+$J29),0)),NA())) | N29: =IF($A29="","",IF(ISNUMBER($J29),IF($E29="CU YD",ROUNDUP(L29*(1+$J29),1),ROUNDUP(L29*(1+$J29),0)),NA())) | O29: =IF($A29="","",IF(ISNUMBER($F29),M29*$F29,NA())) | P29: =IF($A29="","",IF(ISNUMBER($F29),N29*$F29,NA())) | Q29: 1-7/8 gate pipe per LF.
A30: M29 | B30: Gates | C30: Gate frame elbow | D30: 1-7/8 in OD, galvanized (fitted corners option). | E30: EA | F30: 7.5 | G30: Reference estimate | H30: 46307 | J30: 0 | K30: =IF($A30="","",IF(INDEX(Takeoff_In!$D$2:$D$300,MATCH($A30,Takeoff_In!$A$2:$A$300,0))="",NA(),INDEX(Takeoff_In!$D$2:$D$300,MATCH($A30,Takeoff_In!$A$2:$A$300,0)))) | L30: =IF($A30="","",IF(INDEX(Takeoff_In!$E$2:$E$300,MATCH($A30,Takeoff_In!$A$2:$A$300,0))="",NA(),INDEX(Takeoff_In!$E$2:$E$300,MATCH($A30,Takeoff_In!$A$2:$A$300,0)))) | M30: =IF($A30="","",IF(ISNUMBER($J30),IF($E30="CU YD",ROUNDUP(K30*(1+$J30),1),ROUNDUP(K30*(1+$J30),0)),NA())) | N30: =IF($A30="","",IF(ISNUMBER($J30),IF($E30="CU YD",ROUNDUP(L30*(1+$J30),1),ROUNDUP(L30*(1+$J30),0)),NA())) | O30: =IF($A30="","",IF(ISNUMBER($F30),M30*$F30,NA())) | P30: =IF($A30="","",IF(ISNUMBER($F30),N30*$F30,NA()))
A31: M30 | B31: Gates | C31: Gate frame tee | D31: 1-7/8 in OD, galvanized (mid rail connection). | E31: EA | F31: 9.5 | G31: Reference estimate | H31: 46307 | J31: 0 | K31: =IF($A31="","",IF(INDEX(Takeoff_In!$D$2:$D$300,MATCH($A31,Takeoff_In!$A$2:$A$300,0))="",NA(),INDEX(Takeoff_In!$D$2:$D$300,MATCH($A31,Takeoff_In!$A$2:$A$300,0)))) | L31: =IF($A31="","",IF(INDEX(Takeoff_In!$E$2:$E$300,MATCH($A31,Takeoff_In!$A$2:$A$300,0))="",NA(),INDEX(Takeoff_In!$E$2:$E$300,MATCH($A31,Takeoff_In!$A$2:$A$300,0)))) | M31: =IF($A31="","",IF(ISNUMBER($J31),IF($E31="CU YD",ROUNDUP(K31*(1+$J31),1),ROUNDUP(K31*(1+$J31),0)),NA())) | N31: =IF($A31="","",IF(ISNUMBER($J31),IF($E31="CU YD",ROUNDUP(L31*(1+$J31),1),ROUNDUP(L31*(1+$J31),0)),NA())) | O31: =IF($A31="","",IF(ISNUMBER($F31),M31*$F31,NA())) | P31: =IF($A31="","",IF(ISNUMBER($F31),N31*$F31,NA()))
A32: M31 | B32: Gates | C32: Truss rod, gate leaf, adjustable | D32: 3/8 in dia, adjustable, galvanized, one diagonal per leaf. | E32: EA | F32: 11.5 | G32: Reference estimate | H32: 46307 | J32: 0 | K32: =IF($A32="","",IF(INDEX(Takeoff_In!$D$2:$D$300,MATCH($A32,Takeoff_In!$A$2:$A$300,0))="",NA(),INDEX(Takeoff_In!$D$2:$D$300,MATCH($A32,Takeoff_In!$A$2:$A$300,0)))) | L32: =IF($A32="","",IF(INDEX(Takeoff_In!$E$2:$E$300,MATCH($A32,Takeoff_In!$A$2:$A$300,0))="",NA(),INDEX(Takeoff_In!$E$2:$E$300,MATCH($A32,Takeoff_In!$A$2:$A$300,0)))) | M32: =IF($A32="","",IF(ISNUMBER($J32),IF($E32="CU YD",ROUNDUP(K32*(1+$J32),1),ROUNDUP(K32*(1+$J32),0)),NA())) | N32: =IF($A32="","",IF(ISNUMBER($J32),IF($E32="CU YD",ROUNDUP(L32*(1+$J32),1),ROUNDUP(L32*(1+$J32),0)),NA())) | O32: =IF($A32="","",IF(ISNUMBER($F32),M32*$F32,NA())) | P32: =IF($A32="","",IF(ISNUMBER($F32),N32*$F32,NA()))
A33: M32 | B33: Gates | C33: Gate hinge, 180 degree | D33: Malleable, 3 per leaf, to suit 2-7/8 in post and 1-7/8 in frame. | E33: EA | F33: 12 | G33: Reference estimate | H33: 46307 | J33: 0 | K33: =IF($A33="","",IF(INDEX(Takeoff_In!$D$2:$D$300,MATCH($A33,Takeoff_In!$A$2:$A$300,0))="",NA(),INDEX(Takeoff_In!$D$2:$D$300,MATCH($A33,Takeoff_In!$A$2:$A$300,0)))) | L33: =IF($A33="","",IF(INDEX(Takeoff_In!$E$2:$E$300,MATCH($A33,Takeoff_In!$A$2:$A$300,0))="",NA(),INDEX(Takeoff_In!$E$2:$E$300,MATCH($A33,Takeoff_In!$A$2:$A$300,0)))) | M33: =IF($A33="","",IF(ISNUMBER($J33),IF($E33="CU YD",ROUNDUP(K33*(1+$J33),1),ROUNDUP(K33*(1+$J33),0)),NA())) | N33: =IF($A33="","",IF(ISNUMBER($J33),IF($E33="CU YD",ROUNDUP(L33*(1+$J33),1),ROUNDUP(L33*(1+$J33),0)),NA())) | O33: =IF($A33="","",IF(ISNUMBER($F33),M33*$F33,NA())) | P33: =IF($A33="","",IF(ISNUMBER($F33),N33*$F33,NA())) | Q33: Per hinge.
A34: M33 | B34: Gates | C34: Gate latch, industrial fork with padlock eye | D34: Galvanized, for 1-7/8 in frame. | E34: EA | F34: 24 | G34: Reference estimate | H34: 46307 | J34: 0 | K34: =IF($A34="","",IF(INDEX(Takeoff_In!$D$2:$D$300,MATCH($A34,Takeoff_In!$A$2:$A$300,0))="",NA(),INDEX(Takeoff_In!$D$2:$D$300,MATCH($A34,Takeoff_In!$A$2:$A$300,0)))) | L34: =IF($A34="","",IF(INDEX(Takeoff_In!$E$2:$E$300,MATCH($A34,Takeoff_In!$A$2:$A$300,0))="",NA(),INDEX(Takeoff_In!$E$2:$E$300,MATCH($A34,Takeoff_In!$A$2:$A$300,0)))) | M34: =IF($A34="","",IF(ISNUMBER($J34),IF($E34="CU YD",ROUNDUP(K34*(1+$J34),1),ROUNDUP(K34*(1+$J34),0)),NA())) | N34: =IF($A34="","",IF(ISNUMBER($J34),IF($E34="CU YD",ROUNDUP(L34*(1+$J34),1),ROUNDUP(L34*(1+$J34),0)),NA())) | O34: =IF($A34="","",IF(ISNUMBER($F34),M34*$F34,NA())) | P34: =IF($A34="","",IF(ISNUMBER($F34),N34*$F34,NA()))
A35: M34 | B35: Gates | C35: Gate hold-back / stop | D35: Galvanized, per spec 32 31 13 (spec not provided). | E35: EA | F35: 22 | G35: Reference estimate | H35: 46307 | J35: 0 | K35: =IF($A35="","",IF(INDEX(Takeoff_In!$D$2:$D$300,MATCH($A35,Takeoff_In!$A$2:$A$300,0))="",NA(),INDEX(Takeoff_In!$D$2:$D$300,MATCH($A35,Takeoff_In!$A$2:$A$300,0)))) | L35: =IF($A35="","",IF(INDEX(Takeoff_In!$E$2:$E$300,MATCH($A35,Takeoff_In!$A$2:$A$300,0))="",NA(),INDEX(Takeoff_In!$E$2:$E$300,MATCH($A35,Takeoff_In!$A$2:$A$300,0)))) | M35: =IF($A35="","",IF(ISNUMBER($J35),IF($E35="CU YD",ROUNDUP(K35*(1+$J35),1),ROUNDUP(K35*(1+$J35),0)),NA())) | N35: =IF($A35="","",IF(ISNUMBER($J35),IF($E35="CU YD",ROUNDUP(L35*(1+$J35),1),ROUNDUP(L35*(1+$J35),0)),NA())) | O35: =IF($A35="","",IF(ISNUMBER($F35),M35*$F35,NA())) | P35: =IF($A35="","",IF(ISNUMBER($F35),N35*$F35,NA()))
A36: M35 | B36: Gates | C36: Header rail | D36: 1-5/8 in OD, galvanized, across each opening. | E36: LF | F36: 1.9 | G36: Reference estimate | H36: 46307 | J36: 0.05 | K36: =IF($A36="","",IF(INDEX(Takeoff_In!$D$2:$D$300,MATCH($A36,Takeoff_In!$A$2:$A$300,0))="",NA(),INDEX(Takeoff_In!$D$2:$D$300,MATCH($A36,Takeoff_In!$A$2:$A$300,0)))) | L36: =IF($A36="","",IF(INDEX(Takeoff_In!$E$2:$E$300,MATCH($A36,Takeoff_In!$A$2:$A$300,0))="",NA(),INDEX(Takeoff_In!$E$2:$E$300,MATCH($A36,Takeoff_In!$A$2:$A$300,0)))) | M36: =IF($A36="","",IF(ISNUMBER($J36),IF($E36="CU YD",ROUNDUP(K36*(1+$J36),1),ROUNDUP(K36*(1+$J36),0)),NA())) | N36: =IF($A36="","",IF(ISNUMBER($J36),IF($E36="CU YD",ROUNDUP(L36*(1+$J36),1),ROUNDUP(L36*(1+$J36),0)),NA())) | O36: =IF($A36="","",IF(ISNUMBER($F36),M36*$F36,NA())) | P36: =IF($A36="","",IF(ISNUMBER($F36),N36*$F36,NA()))
A37: M36 | B37: Gates | C37: Tension bar, gate leaf | D37: 3/16 x 3/4 in flat bar, about 80 in long (7 ft leaf). | E37: EA | F37: 6.4 | G37: Reference estimate | H37: 46307 | J37: 0.1 | K37: =IF($A37="","",IF(INDEX(Takeoff_In!$D$2:$D$300,MATCH($A37,Takeoff_In!$A$2:$A$300,0))="",NA(),INDEX(Takeoff_In!$D$2:$D$300,MATCH($A37,Takeoff_In!$A$2:$A$300,0)))) | L37: =IF($A37="","",IF(INDEX(Takeoff_In!$E$2:$E$300,MATCH($A37,Takeoff_In!$A$2:$A$300,0))="",NA(),INDEX(Takeoff_In!$E$2:$E$300,MATCH($A37,Takeoff_In!$A$2:$A$300,0)))) | M37: =IF($A37="","",IF(ISNUMBER($J37),IF($E37="CU YD",ROUNDUP(K37*(1+$J37),1),ROUNDUP(K37*(1+$J37),0)),NA())) | N37: =IF($A37="","",IF(ISNUMBER($J37),IF($E37="CU YD",ROUNDUP(L37*(1+$J37),1),ROUNDUP(L37*(1+$J37),0)),NA())) | O37: =IF($A37="","",IF(ISNUMBER($F37),M37*$F37,NA())) | P37: =IF($A37="","",IF(ISNUMBER($F37),N37*$F37,NA()))
A38: M37 | B38: Gates | C38: Tension band, 1-7/8 in frame | D38: For 3/4 in tension bar on 1-7/8 in OD gate frame. | E38: EA | F38: 1.3 | G38: Reference estimate | H38: 46307 | J38: 0.1 | K38: =IF($A38="","",IF(INDEX(Takeoff_In!$D$2:$D$300,MATCH($A38,Takeoff_In!$A$2:$A$300,0))="",NA(),INDEX(Takeoff_In!$D$2:$D$300,MATCH($A38,Takeoff_In!$A$2:$A$300,0)))) | L38: =IF($A38="","",IF(INDEX(Takeoff_In!$E$2:$E$300,MATCH($A38,Takeoff_In!$A$2:$A$300,0))="",NA(),INDEX(Takeoff_In!$E$2:$E$300,MATCH($A38,Takeoff_In!$A$2:$A$300,0)))) | M38: =IF($A38="","",IF(ISNUMBER($J38),IF($E38="CU YD",ROUNDUP(K38*(1+$J38),1),ROUNDUP(K38*(1+$J38),0)),NA())) | N38: =IF($A38="","",IF(ISNUMBER($J38),IF($E38="CU YD",ROUNDUP(L38*(1+$J38),1),ROUNDUP(L38*(1+$J38),0)),NA())) | O38: =IF($A38="","",IF(ISNUMBER($F38),M38*$F38,NA())) | P38: =IF($A38="","",IF(ISNUMBER($F38),N38*$F38,NA()))
A39: M38 | B39: Windscreen | C39: Windscreen | D39: Knitted polypropylene, 88% nominal shade, reinforced hems, brass grommets at 12 in o.c. top and bottom, 9 ft high. | E39: LF | F39: 2.5 | G39: Reference estimate | H39: 46307 | J39: 0.05 | K39: =IF($A39="","",IF(INDEX(Takeoff_In!$D$2:$D$300,MATCH($A39,Takeoff_In!$A$2:$A$300,0))="",NA(),INDEX(Takeoff_In!$D$2:$D$300,MATCH($A39,Takeoff_In!$A$2:$A$300,0)))) | L39: =IF($A39="","",IF(INDEX(Takeoff_In!$E$2:$E$300,MATCH($A39,Takeoff_In!$A$2:$A$300,0))="",NA(),INDEX(Takeoff_In!$E$2:$E$300,MATCH($A39,Takeoff_In!$A$2:$A$300,0)))) | M39: =IF($A39="","",IF(ISNUMBER($J39),IF($E39="CU YD",ROUNDUP(K39*(1+$J39),1),ROUNDUP(K39*(1+$J39),0)),NA())) | N39: =IF($A39="","",IF(ISNUMBER($J39),IF($E39="CU YD",ROUNDUP(L39*(1+$J39),1),ROUNDUP(L39*(1+$J39),0)),NA())) | O39: =IF($A39="","",IF(ISNUMBER($F39),M39*$F39,NA())) | P39: =IF($A39="","",IF(ISNUMBER($F39),N39*$F39,NA())) | Q39: 9 ft knitted, grommeted. Estimate per LF.
A40: M39 | B40: Windscreen | C40: Cable tie, UV-resistant nylon | D40: Heavy-duty (about 14 in), UV black. One per grommet. | E40: EA | F40: 0.09 | G40: Reference estimate | H40: 46307 | J40: 0.1 | K40: =IF($A40="","",IF(INDEX(Takeoff_In!$D$2:$D$300,MATCH($A40,Takeoff_In!$A$2:$A$300,0))="",NA(),INDEX(Takeoff_In!$D$2:$D$300,MATCH($A40,Takeoff_In!$A$2:$A$300,0)))) | L40: =IF($A40="","",IF(INDEX(Takeoff_In!$E$2:$E$300,MATCH($A40,Takeoff_In!$A$2:$A$300,0))="",NA(),INDEX(Takeoff_In!$E$2:$E$300,MATCH($A40,Takeoff_In!$A$2:$A$300,0)))) | M40: =IF($A40="","",IF(ISNUMBER($J40),IF($E40="CU YD",ROUNDUP(K40*(1+$J40),1),ROUNDUP(K40*(1+$J40),0)),NA())) | N40: =IF($A40="","",IF(ISNUMBER($J40),IF($E40="CU YD",ROUNDUP(L40*(1+$J40),1),ROUNDUP(L40*(1+$J40),0)),NA())) | O40: =IF($A40="","",IF(ISNUMBER($F40),M40*$F40,NA())) | P40: =IF($A40="","",IF(ISNUMBER($F40),N40*$F40,NA()))
A41: M40 | B41: Concrete | C41: Ready-mix concrete | D41: Strength / slump per Section 32 31 13 (spec not provided). | E41: CU YD | F41: 185 | G41: Reference estimate | H41: 46307 | J41: 0.1 | K41: =IF($A41="","",IF(INDEX(Takeoff_In!$D$2:$D$300,MATCH($A41,Takeoff_In!$A$2:$A$300,0))="",NA(),INDEX(Takeoff_In!$D$2:$D$300,MATCH($A41,Takeoff_In!$A$2:$A$300,0)))) | L41: =IF($A41="","",IF(INDEX(Takeoff_In!$E$2:$E$300,MATCH($A41,Takeoff_In!$A$2:$A$300,0))="",NA(),INDEX(Takeoff_In!$E$2:$E$300,MATCH($A41,Takeoff_In!$A$2:$A$300,0)))) | M41: =IF($A41="","",IF(ISNUMBER($J41),IF($E41="CU YD",ROUNDUP(K41*(1+$J41),1),ROUNDUP(K41*(1+$J41),0)),NA())) | N41: =IF($A41="","",IF(ISNUMBER($J41),IF($E41="CU YD",ROUNDUP(L41*(1+$J41),1),ROUNDUP(L41*(1+$J41),0)),NA())) | O41: =IF($A41="","",IF(ISNUMBER($F41),M41*$F41,NA())) | P41: =IF($A41="","",IF(ISNUMBER($F41),N41*$F41,NA())) | Q41: 3000 psi. No short-load fee included. Estimate, not verified for Iowa. Sole concrete supply item; M41 (bagged concrete) is retired and its ID is not reused.
A42: M42 | B42: Accessories | C42: Fence guard, UV-stabilized polyethylene, on Type B top rail | D42: Standard-wall polyethylene cover, owner-selected color, per linear foot. | E42: LF | F42: 1.85 | G42: Reference estimate | H42: 46307 | I42: reference estimate | J42: 0.05 | K42: =IF($A42="","",IF(INDEX(Takeoff_In!$D$2:$D$300,MATCH($A42,Takeoff_In!$A$2:$A$300,0))="",NA(),INDEX(Takeoff_In!$D$2:$D$300,MATCH($A42,Takeoff_In!$A$2:$A$300,0)))) | L42: =IF($A42="","",IF(INDEX(Takeoff_In!$E$2:$E$300,MATCH($A42,Takeoff_In!$A$2:$A$300,0))="",NA(),INDEX(Takeoff_In!$E$2:$E$300,MATCH($A42,Takeoff_In!$A$2:$A$300,0)))) | M42: =IF($A42="","",IF(ISNUMBER($J42),IF($E42="CU YD",ROUNDUP(K42*(1+$J42),1),ROUNDUP(K42*(1+$J42),0)),NA())) | N42: =IF($A42="","",IF(ISNUMBER($J42),IF($E42="CU YD",ROUNDUP(L42*(1+$J42),1),ROUNDUP(L42*(1+$J42),0)),NA())) | O42: =IF($A42="","",IF(ISNUMBER($F42),M42*$F42,NA())) | P42: =IF($A42="","",IF(ISNUMBER($F42),N42*$F42,NA())) | Q42: Fictional reference estimate; not a vendor quote.
A43: M43 | B43: Gates | C43: Gate center drop rod, double-leaf gate | D43: Galvanized drop rod with fork keeper; one per double-leaf gate. | E43: EA | F43: 38 | G43: Reference estimate | H43: 46307 | I43: reference estimate | J43: 0 | K43: =IF($A43="","",IF(INDEX(Takeoff_In!$D$2:$D$300,MATCH($A43,Takeoff_In!$A$2:$A$300,0))="",NA(),INDEX(Takeoff_In!$D$2:$D$300,MATCH($A43,Takeoff_In!$A$2:$A$300,0)))) | L43: =IF($A43="","",IF(INDEX(Takeoff_In!$E$2:$E$300,MATCH($A43,Takeoff_In!$A$2:$A$300,0))="",NA(),INDEX(Takeoff_In!$E$2:$E$300,MATCH($A43,Takeoff_In!$A$2:$A$300,0)))) | M43: =IF($A43="","",IF(ISNUMBER($J43),IF($E43="CU YD",ROUNDUP(K43*(1+$J43),1),ROUNDUP(K43*(1+$J43),0)),NA())) | N43: =IF($A43="","",IF(ISNUMBER($J43),IF($E43="CU YD",ROUNDUP(L43*(1+$J43),1),ROUNDUP(L43*(1+$J43),0)),NA())) | O43: =IF($A43="","",IF(ISNUMBER($F43),M43*$F43,NA())) | P43: =IF($A43="","",IF(ISNUMBER($F43),N43*$F43,NA())) | Q43: Fictional reference estimate; not a vendor quote.
A44: M44 | B44: Gates | C44: Gate ground socket, for center drop rod | D44: Ground socket for the drop rod; set in the gate footing/pavement. | E44: EA | F44: 14.5 | G44: Reference estimate | H44: 46307 | I44: reference estimate | J44: 0 | K44: =IF($A44="","",IF(INDEX(Takeoff_In!$D$2:$D$300,MATCH($A44,Takeoff_In!$A$2:$A$300,0))="",NA(),INDEX(Takeoff_In!$D$2:$D$300,MATCH($A44,Takeoff_In!$A$2:$A$300,0)))) | L44: =IF($A44="","",IF(INDEX(Takeoff_In!$E$2:$E$300,MATCH($A44,Takeoff_In!$A$2:$A$300,0))="",NA(),INDEX(Takeoff_In!$E$2:$E$300,MATCH($A44,Takeoff_In!$A$2:$A$300,0)))) | M44: =IF($A44="","",IF(ISNUMBER($J44),IF($E44="CU YD",ROUNDUP(K44*(1+$J44),1),ROUNDUP(K44*(1+$J44),0)),NA())) | N44: =IF($A44="","",IF(ISNUMBER($J44),IF($E44="CU YD",ROUNDUP(L44*(1+$J44),1),ROUNDUP(L44*(1+$J44),0)),NA())) | O44: =IF($A44="","",IF(ISNUMBER($F44),M44*$F44,NA())) | P44: =IF($A44="","",IF(ISNUMBER($F44),N44*$F44,NA())) | Q44: Fictional reference estimate; not a vendor quote.
K45: =IF($A45="","",IF(INDEX(Takeoff_In!$D$2:$D$300,MATCH($A45,Takeoff_In!$A$2:$A$300,0))="",NA(),INDEX(Takeoff_In!$D$2:$D$300,MATCH($A45,Takeoff_In!$A$2:$A$300,0)))) | L45: =IF($A45="","",IF(INDEX(Takeoff_In!$E$2:$E$300,MATCH($A45,Takeoff_In!$A$2:$A$300,0))="",NA(),INDEX(Takeoff_In!$E$2:$E$300,MATCH($A45,Takeoff_In!$A$2:$A$300,0)))) | M45: =IF($A45="","",IF(ISNUMBER($J45),IF($E45="CU YD",ROUNDUP(K45*(1+$J45),1),ROUNDUP(K45*(1+$J45),0)),NA())) | N45: =IF($A45="","",IF(ISNUMBER($J45),IF($E45="CU YD",ROUNDUP(L45*(1+$J45),1),ROUNDUP(L45*(1+$J45),0)),NA())) | O45: =IF($A45="","",IF(ISNUMBER($F45),M45*$F45,NA())) | P45: =IF($A45="","",IF(ISNUMBER($F45),N45*$F45,NA()))
K46: =IF($A46="","",IF(INDEX(Takeoff_In!$D$2:$D$300,MATCH($A46,Takeoff_In!$A$2:$A$300,0))="",NA(),INDEX(Takeoff_In!$D$2:$D$300,MATCH($A46,Takeoff_In!$A$2:$A$300,0)))) | L46: =IF($A46="","",IF(INDEX(Takeoff_In!$E$2:$E$300,MATCH($A46,Takeoff_In!$A$2:$A$300,0))="",NA(),INDEX(Takeoff_In!$E$2:$E$300,MATCH($A46,Takeoff_In!$A$2:$A$300,0)))) | M46: =IF($A46="","",IF(ISNUMBER($J46),IF($E46="CU YD",ROUNDUP(K46*(1+$J46),1),ROUNDUP(K46*(1+$J46),0)),NA())) | N46: =IF($A46="","",IF(ISNUMBER($J46),IF($E46="CU YD",ROUNDUP(L46*(1+$J46),1),ROUNDUP(L46*(1+$J46),0)),NA())) | O46: =IF($A46="","",IF(ISNUMBER($F46),M46*$F46,NA())) | P46: =IF($A46="","",IF(ISNUMBER($F46),N46*$F46,NA()))
K47: =IF($A47="","",IF(INDEX(Takeoff_In!$D$2:$D$300,MATCH($A47,Takeoff_In!$A$2:$A$300,0))="",NA(),INDEX(Takeoff_In!$D$2:$D$300,MATCH($A47,Takeoff_In!$A$2:$A$300,0)))) | L47: =IF($A47="","",IF(INDEX(Takeoff_In!$E$2:$E$300,MATCH($A47,Takeoff_In!$A$2:$A$300,0))="",NA(),INDEX(Takeoff_In!$E$2:$E$300,MATCH($A47,Takeoff_In!$A$2:$A$300,0)))) | M47: =IF($A47="","",IF(ISNUMBER($J47),IF($E47="CU YD",ROUNDUP(K47*(1+$J47),1),ROUNDUP(K47*(1+$J47),0)),NA())) | N47: =IF($A47="","",IF(ISNUMBER($J47),IF($E47="CU YD",ROUNDUP(L47*(1+$J47),1),ROUNDUP(L47*(1+$J47),0)),NA())) | O47: =IF($A47="","",IF(ISNUMBER($F47),M47*$F47,NA())) | P47: =IF($A47="","",IF(ISNUMBER($F47),N47*$F47,NA()))
K48: =IF($A48="","",IF(INDEX(Takeoff_In!$D$2:$D$300,MATCH($A48,Takeoff_In!$A$2:$A$300,0))="",NA(),INDEX(Takeoff_In!$D$2:$D$300,MATCH($A48,Takeoff_In!$A$2:$A$300,0)))) | L48: =IF($A48="","",IF(INDEX(Takeoff_In!$E$2:$E$300,MATCH($A48,Takeoff_In!$A$2:$A$300,0))="",NA(),INDEX(Takeoff_In!$E$2:$E$300,MATCH($A48,Takeoff_In!$A$2:$A$300,0)))) | M48: =IF($A48="","",IF(ISNUMBER($J48),IF($E48="CU YD",ROUNDUP(K48*(1+$J48),1),ROUNDUP(K48*(1+$J48),0)),NA())) | N48: =IF($A48="","",IF(ISNUMBER($J48),IF($E48="CU YD",ROUNDUP(L48*(1+$J48),1),ROUNDUP(L48*(1+$J48),0)),NA())) | O48: =IF($A48="","",IF(ISNUMBER($F48),M48*$F48,NA())) | P48: =IF($A48="","",IF(ISNUMBER($F48),N48*$F48,NA()))
K49: =IF($A49="","",IF(INDEX(Takeoff_In!$D$2:$D$300,MATCH($A49,Takeoff_In!$A$2:$A$300,0))="",NA(),INDEX(Takeoff_In!$D$2:$D$300,MATCH($A49,Takeoff_In!$A$2:$A$300,0)))) | L49: =IF($A49="","",IF(INDEX(Takeoff_In!$E$2:$E$300,MATCH($A49,Takeoff_In!$A$2:$A$300,0))="",NA(),INDEX(Takeoff_In!$E$2:$E$300,MATCH($A49,Takeoff_In!$A$2:$A$300,0)))) | M49: =IF($A49="","",IF(ISNUMBER($J49),IF($E49="CU YD",ROUNDUP(K49*(1+$J49),1),ROUNDUP(K49*(1+$J49),0)),NA())) | N49: =IF($A49="","",IF(ISNUMBER($J49),IF($E49="CU YD",ROUNDUP(L49*(1+$J49),1),ROUNDUP(L49*(1+$J49),0)),NA())) | O49: =IF($A49="","",IF(ISNUMBER($F49),M49*$F49,NA())) | P49: =IF($A49="","",IF(ISNUMBER($F49),N49*$F49,NA()))
K50: =IF($A50="","",IF(INDEX(Takeoff_In!$D$2:$D$300,MATCH($A50,Takeoff_In!$A$2:$A$300,0))="",NA(),INDEX(Takeoff_In!$D$2:$D$300,MATCH($A50,Takeoff_In!$A$2:$A$300,0)))) | L50: =IF($A50="","",IF(INDEX(Takeoff_In!$E$2:$E$300,MATCH($A50,Takeoff_In!$A$2:$A$300,0))="",NA(),INDEX(Takeoff_In!$E$2:$E$300,MATCH($A50,Takeoff_In!$A$2:$A$300,0)))) | M50: =IF($A50="","",IF(ISNUMBER($J50),IF($E50="CU YD",ROUNDUP(K50*(1+$J50),1),ROUNDUP(K50*(1+$J50),0)),NA())) | N50: =IF($A50="","",IF(ISNUMBER($J50),IF($E50="CU YD",ROUNDUP(L50*(1+$J50),1),ROUNDUP(L50*(1+$J50),0)),NA())) | O50: =IF($A50="","",IF(ISNUMBER($F50),M50*$F50,NA())) | P50: =IF($A50="","",IF(ISNUMBER($F50),N50*$F50,NA()))
K51: =IF($A51="","",IF(INDEX(Takeoff_In!$D$2:$D$300,MATCH($A51,Takeoff_In!$A$2:$A$300,0))="",NA(),INDEX(Takeoff_In!$D$2:$D$300,MATCH($A51,Takeoff_In!$A$2:$A$300,0)))) | L51: =IF($A51="","",IF(INDEX(Takeoff_In!$E$2:$E$300,MATCH($A51,Takeoff_In!$A$2:$A$300,0))="",NA(),INDEX(Takeoff_In!$E$2:$E$300,MATCH($A51,Takeoff_In!$A$2:$A$300,0)))) | M51: =IF($A51="","",IF(ISNUMBER($J51),IF($E51="CU YD",ROUNDUP(K51*(1+$J51),1),ROUNDUP(K51*(1+$J51),0)),NA())) | N51: =IF($A51="","",IF(ISNUMBER($J51),IF($E51="CU YD",ROUNDUP(L51*(1+$J51),1),ROUNDUP(L51*(1+$J51),0)),NA())) | O51: =IF($A51="","",IF(ISNUMBER($F51),M51*$F51,NA())) | P51: =IF($A51="","",IF(ISNUMBER($F51),N51*$F51,NA()))
K52: =IF($A52="","",IF(INDEX(Takeoff_In!$D$2:$D$300,MATCH($A52,Takeoff_In!$A$2:$A$300,0))="",NA(),INDEX(Takeoff_In!$D$2:$D$300,MATCH($A52,Takeoff_In!$A$2:$A$300,0)))) | L52: =IF($A52="","",IF(INDEX(Takeoff_In!$E$2:$E$300,MATCH($A52,Takeoff_In!$A$2:$A$300,0))="",NA(),INDEX(Takeoff_In!$E$2:$E$300,MATCH($A52,Takeoff_In!$A$2:$A$300,0)))) | M52: =IF($A52="","",IF(ISNUMBER($J52),IF($E52="CU YD",ROUNDUP(K52*(1+$J52),1),ROUNDUP(K52*(1+$J52),0)),NA())) | N52: =IF($A52="","",IF(ISNUMBER($J52),IF($E52="CU YD",ROUNDUP(L52*(1+$J52),1),ROUNDUP(L52*(1+$J52),0)),NA())) | O52: =IF($A52="","",IF(ISNUMBER($F52),M52*$F52,NA())) | P52: =IF($A52="","",IF(ISNUMBER($F52),N52*$F52,NA()))
K53: =IF($A53="","",IF(INDEX(Takeoff_In!$D$2:$D$300,MATCH($A53,Takeoff_In!$A$2:$A$300,0))="",NA(),INDEX(Takeoff_In!$D$2:$D$300,MATCH($A53,Takeoff_In!$A$2:$A$300,0)))) | L53: =IF($A53="","",IF(INDEX(Takeoff_In!$E$2:$E$300,MATCH($A53,Takeoff_In!$A$2:$A$300,0))="",NA(),INDEX(Takeoff_In!$E$2:$E$300,MATCH($A53,Takeoff_In!$A$2:$A$300,0)))) | M53: =IF($A53="","",IF(ISNUMBER($J53),IF($E53="CU YD",ROUNDUP(K53*(1+$J53),1),ROUNDUP(K53*(1+$J53),0)),NA())) | N53: =IF($A53="","",IF(ISNUMBER($J53),IF($E53="CU YD",ROUNDUP(L53*(1+$J53),1),ROUNDUP(L53*(1+$J53),0)),NA())) | O53: =IF($A53="","",IF(ISNUMBER($F53),M53*$F53,NA())) | P53: =IF($A53="","",IF(ISNUMBER($F53),N53*$F53,NA()))
K54: =IF($A54="","",IF(INDEX(Takeoff_In!$D$2:$D$300,MATCH($A54,Takeoff_In!$A$2:$A$300,0))="",NA(),INDEX(Takeoff_In!$D$2:$D$300,MATCH($A54,Takeoff_In!$A$2:$A$300,0)))) | L54: =IF($A54="","",IF(INDEX(Takeoff_In!$E$2:$E$300,MATCH($A54,Takeoff_In!$A$2:$A$300,0))="",NA(),INDEX(Takeoff_In!$E$2:$E$300,MATCH($A54,Takeoff_In!$A$2:$A$300,0)))) | M54: =IF($A54="","",IF(ISNUMBER($J54),IF($E54="CU YD",ROUNDUP(K54*(1+$J54),1),ROUNDUP(K54*(1+$J54),0)),NA())) | N54: =IF($A54="","",IF(ISNUMBER($J54),IF($E54="CU YD",ROUNDUP(L54*(1+$J54),1),ROUNDUP(L54*(1+$J54),0)),NA())) | O54: =IF($A54="","",IF(ISNUMBER($F54),M54*$F54,NA())) | P54: =IF($A54="","",IF(ISNUMBER($F54),N54*$F54,NA()))
K55: =IF($A55="","",IF(INDEX(Takeoff_In!$D$2:$D$300,MATCH($A55,Takeoff_In!$A$2:$A$300,0))="",NA(),INDEX(Takeoff_In!$D$2:$D$300,MATCH($A55,Takeoff_In!$A$2:$A$300,0)))) | L55: =IF($A55="","",IF(INDEX(Takeoff_In!$E$2:$E$300,MATCH($A55,Takeoff_In!$A$2:$A$300,0))="",NA(),INDEX(Takeoff_In!$E$2:$E$300,MATCH($A55,Takeoff_In!$A$2:$A$300,0)))) | M55: =IF($A55="","",IF(ISNUMBER($J55),IF($E55="CU YD",ROUNDUP(K55*(1+$J55),1),ROUNDUP(K55*(1+$J55),0)),NA())) | N55: =IF($A55="","",IF(ISNUMBER($J55),IF($E55="CU YD",ROUNDUP(L55*(1+$J55),1),ROUNDUP(L55*(1+$J55),0)),NA())) | O55: =IF($A55="","",IF(ISNUMBER($F55),M55*$F55,NA())) | P55: =IF($A55="","",IF(ISNUMBER($F55),N55*$F55,NA()))
K56: =IF($A56="","",IF(INDEX(Takeoff_In!$D$2:$D$300,MATCH($A56,Takeoff_In!$A$2:$A$300,0))="",NA(),INDEX(Takeoff_In!$D$2:$D$300,MATCH($A56,Takeoff_In!$A$2:$A$300,0)))) | L56: =IF($A56="","",IF(INDEX(Takeoff_In!$E$2:$E$300,MATCH($A56,Takeoff_In!$A$2:$A$300,0))="",NA(),INDEX(Takeoff_In!$E$2:$E$300,MATCH($A56,Takeoff_In!$A$2:$A$300,0)))) | M56: =IF($A56="","",IF(ISNUMBER($J56),IF($E56="CU YD",ROUNDUP(K56*(1+$J56),1),ROUNDUP(K56*(1+$J56),0)),NA())) | N56: =IF($A56="","",IF(ISNUMBER($J56),IF($E56="CU YD",ROUNDUP(L56*(1+$J56),1),ROUNDUP(L56*(1+$J56),0)),NA())) | O56: =IF($A56="","",IF(ISNUMBER($F56),M56*$F56,NA())) | P56: =IF($A56="","",IF(ISNUMBER($F56),N56*$F56,NA()))
... K200: =IF($A200="","",IF(INDEX(Takeoff_In!$D$2:$D$300,MATCH($A200,Takeoff_In!$A$2:$A$300,0))="",NA(),INDEX(Takeoff_In!$D$2:$D$300,MATCH($A200,Takeoff_In!$A$2:$A$300,0)))) | L200: =IF($A200="","",IF(INDEX(Takeoff_In!$E$2:$E$300,MATCH($A200,Takeoff_In!$A$2:$A$300,0))="",NA(),INDEX(Takeoff_In!$E$2:$E$300,MATCH($A200,Takeoff_In!$A$2:$A$300,0)))) | M200: =IF($A200="","",IF(ISNUMBER($J200),IF($E200="CU YD",ROUNDUP(K200*(1+$J200),1),ROUNDUP(K200*(1+$J200),0)),NA())) | N200: =IF($A200="","",IF(ISNUMBER($J200),IF($E200="CU YD",ROUNDUP(L200*(1+$J200),1),ROUNDUP(L200*(1+$J200),0)),NA())) | O200: =IF($A200="","",IF(ISNUMBER($F200),M200*$F200,NA())) | P200: =IF($A200="","",IF(ISNUMBER($F200),N200*$F200,NA()))

Sheet Roles
A1: role_key | B1: role | C1: base_wage_per_hr | D1: burden_pct (taxes, comp, ins, benefits) | E1: loaded_rate_per_hr
A2: R1 | B2: Foreman | C2: 32 | D2: 0.35 | E2: =IF(AND(C2="",D2=""),0,IF(AND(ISNUMBER(C2),ISNUMBER(D2)),C2*(1+D2),NA()))
A3: R2 | B3: Installer | C3: 26 | D3: 0.35 | E3: =IF(AND(C3="",D3=""),0,IF(AND(ISNUMBER(C3),ISNUMBER(D3)),C3*(1+D3),NA()))
A4: R3 | B4: Laborer | C4: 20 | D4: 0.35 | E4: =IF(AND(C4="",D4=""),0,IF(AND(ISNUMBER(C4),ISNUMBER(D4)),C4*(1+D4),NA()))
A5: R4 | B5: Equipment operator | C5: 28 | D5: 0.35 | E5: =IF(AND(C5="",D5=""),0,IF(AND(ISNUMBER(C5),ISNUMBER(D5)),C5*(1+D5),NA()))
A6: R5 | E6: =IF(AND(C6="",D6=""),0,IF(AND(ISNUMBER(C6),ISNUMBER(D6)),C6*(1+D6),NA()))
A7: R6 | E7: =IF(AND(C7="",D7=""),0,IF(AND(ISNUMBER(C7),ISNUMBER(D7)),C7*(1+D7),NA()))

Sheet Crews
A1: crew_id | B1: description | C1: n_R1_foreman | D1: n_R2_installer | E1: n_R3_laborer | F1: n_R4_operator | G1: headcount | H1: loaded_rate_per_crew_hr | I1: efficiency_pct | J1: difficulty_easy | K1: difficulty_standard | L1: difficulty_hard | M1: qualifications | N1: profile_version
A2: CR1 | B2: Layout and drill crew | C2: 1 | D2: 0 | E2: 1 | F2: 1 | G2: =SUM(C2:F2) | H2: =IF(COUNT(C2:F2)=0,0,IF(COUNT(C2:F2)=4,C2*Roles!$E$2+D2*Roles!$E$3+E2*Roles!$E$4+F2*Roles!$E$5,NA())) | I2: 100 | J2: 1 | K2: 1 | L2: 1 | N2: 1
A3: CR2 | B3: Post and rail crew | C3: 1 | D3: 2 | E3: 1 | F3: 0 | G3: =SUM(C3:F3) | H3: =IF(COUNT(C3:F3)=0,0,IF(COUNT(C3:F3)=4,C3*Roles!$E$2+D3*Roles!$E$3+E3*Roles!$E$4+F3*Roles!$E$5,NA())) | I3: 100 | J3: 1 | K3: 1 | L3: 1 | N3: 1
A4: CR3 | B4: Fabric and gate crew | C4: 1 | D4: 2 | E4: 1 | F4: 0 | G4: =SUM(C4:F4) | H4: =IF(COUNT(C4:F4)=0,0,IF(COUNT(C4:F4)=4,C4*Roles!$E$2+D4*Roles!$E$3+E4*Roles!$E$4+F4*Roles!$E$5,NA())) | I4: 100 | J4: 1 | K4: 1 | L4: 1 | N4: 1
A5: CR4 | B5: Windscreen and finish crew | C5: 0 | D5: 1 | E5: 2 | F5: 0 | G5: =SUM(C5:F5) | H5: =IF(COUNT(C5:F5)=0,0,IF(COUNT(C5:F5)=4,C5*Roles!$E$2+D5*Roles!$E$3+E5*Roles!$E$4+F5*Roles!$E$5,NA())) | I5: 100 | J5: 1 | K5: 1 | L5: 1 | N5: 1
A6: CR5 | G6: =SUM(C6:F6) | H6: =IF(COUNT(C6:F6)=0,0,IF(COUNT(C6:F6)=4,C6*Roles!$E$2+D6*Roles!$E$3+E6*Roles!$E$4+F6*Roles!$E$5,NA()))
A7: CR6 | G7: =SUM(C7:F7) | H7: =IF(COUNT(C7:F7)=0,0,IF(COUNT(C7:F7)=4,C7*Roles!$E$2+D7*Roles!$E$3+E7*Roles!$E$4+F7*Roles!$E$5,NA()))
A8: CR11 | B8: Crew 1: foreman + 2 laborers | C8: 1 | D8: 0 | E8: 2 | F8: 0 | G8: =SUM(C8:F8) | H8: =IF(COUNT(C8:F8)=0,0,IF(COUNT(C8:F8)=4,C8*Roles!$E$2+D8*Roles!$E$3+E8*Roles!$E$4+F8*Roles!$E$5,NA())) | I8: 104 | J8: 1.1 | K8: 1 | L8: 0.8 | N8: A1
A9: CR12 | B9: Crew 2: specialized fence crew | C9: 1 | D9: 2 | E9: 1 | F9: 0 | G9: =SUM(C9:F9) | H9: =IF(COUNT(C9:F9)=0,0,IF(COUNT(C9:F9)=4,C9*Roles!$E$2+D9*Roles!$E$3+E9*Roles!$E$4+F9*Roles!$E$5,NA())) | I9: 94 | J9: 1.03 | K9: 1 | L9: 0.95 | N9: B1
A10: CR13 | B10: Crew 3: installers + operator | C10: 0 | D10: 2 | E10: 0 | F10: 1 | G10: =SUM(C10:F10) | H10: =IF(COUNT(C10:F10)=0,0,IF(COUNT(C10:F10)=4,C10*Roles!$E$2+D10*Roles!$E$3+E10*Roles!$E$4+F10*Roles!$E$5,NA())) | I10: 88 | J10: 1 | K10: 1 | L10: 0.97 | N10: C1
A11: CR14 | B11: Crew 4: foreman, installers + operator | C11: 1 | D11: 2 | E11: 0 | F11: 1 | G11: =SUM(C11:F11) | H11: =IF(COUNT(C11:F11)=0,0,IF(COUNT(C11:F11)=4,C11*Roles!$E$2+D11*Roles!$E$3+E11*Roles!$E$4+F11*Roles!$E$5,NA())) | I11: 97 | J11: 1.05 | K11: 1 | L11: 0.92 | N11: D1

Sheet Labor
A1: task_id | B1: task | C1: driver_key | D1: uom | E1: crew_id | F1: production_rate (uom per crew-hr) | G1: qty_base | H1: qty_alt | I1: crew_hrs_base | J1: crew_hrs_alt | K1: crew_rate_per_hr | L1: labor_base | M1: labor_alt | N1: per_unit_base | O1: notes | P1: rate_basis | Q1: required_roles | R1: required_qualifications
A2: L01 | B2: Layout and stakeout | C2: D12 | D2: =IF($C2="","",INDEX(Takeoff_In!$C$2:$C$300,MATCH($C2,Takeoff_In!$A$2:$A$300,0))) | E2: CR1 | F2: 150 | G2: =IF($C2="","",IF(INDEX(Takeoff_In!$D$2:$D$300,MATCH($C2,Takeoff_In!$A$2:$A$300,0))="",NA(),INDEX(Takeoff_In!$D$2:$D$300,MATCH($C2,Takeoff_In!$A$2:$A$300,0)))) | H2: =IF($C2="","",IF(INDEX(Takeoff_In!$E$2:$E$300,MATCH($C2,Takeoff_In!$A$2:$A$300,0))="",NA(),INDEX(Takeoff_In!$E$2:$E$300,MATCH($C2,Takeoff_In!$A$2:$A$300,0)))) | I2: =IF($C2="",0,IF(AND(ISNUMBER($F2),$F2>0),G2/$F2,NA())) | J2: =IF($C2="",0,IF(AND(ISNUMBER($F2),$F2>0),H2/$F2,NA())) | K2: =IF($C2="",0,INDEX(Crews!$H$2:$H$20,MATCH($E2,Crews!$A$2:$A$20,0))) | L2: =IF($C2="",0,I2*K2) | M2: =IF($C2="",0,J2*K2) | N2: =IF($C2="",0,IF(G2=0,0,L2/G2)) | P2: standard
A3: L02 | B3: Drill post holes | C3: D04 | D3: =IF($C3="","",INDEX(Takeoff_In!$C$2:$C$300,MATCH($C3,Takeoff_In!$A$2:$A$300,0))) | E3: CR1 | F3: 8 | G3: =IF($C3="","",IF(INDEX(Takeoff_In!$D$2:$D$300,MATCH($C3,Takeoff_In!$A$2:$A$300,0))="",NA(),INDEX(Takeoff_In!$D$2:$D$300,MATCH($C3,Takeoff_In!$A$2:$A$300,0)))) | H3: =IF($C3="","",IF(INDEX(Takeoff_In!$E$2:$E$300,MATCH($C3,Takeoff_In!$A$2:$A$300,0))="",NA(),INDEX(Takeoff_In!$E$2:$E$300,MATCH($C3,Takeoff_In!$A$2:$A$300,0)))) | I3: =IF($C3="",0,IF(AND(ISNUMBER($F3),$F3>0),G3/$F3,NA())) | J3: =IF($C3="",0,IF(AND(ISNUMBER($F3),$F3>0),H3/$F3,NA())) | K3: =IF($C3="",0,INDEX(Crews!$H$2:$H$20,MATCH($E3,Crews!$A$2:$A$20,0))) | L3: =IF($C3="",0,I3*K3) | M3: =IF($C3="",0,J3*K3) | N3: =IF($C3="",0,IF(G3=0,0,L3/G3)) | P3: standard | Q3: R4
A4: L03 | B4: Set posts, plumb, pour concrete | C4: D03 | D4: =IF($C4="","",INDEX(Takeoff_In!$C$2:$C$300,MATCH($C4,Takeoff_In!$A$2:$A$300,0))) | E4: CR2 | F4: 6 | G4: =IF($C4="","",IF(INDEX(Takeoff_In!$D$2:$D$300,MATCH($C4,Takeoff_In!$A$2:$A$300,0))="",NA(),INDEX(Takeoff_In!$D$2:$D$300,MATCH($C4,Takeoff_In!$A$2:$A$300,0)))) | H4: =IF($C4="","",IF(INDEX(Takeoff_In!$E$2:$E$300,MATCH($C4,Takeoff_In!$A$2:$A$300,0))="",NA(),INDEX(Takeoff_In!$E$2:$E$300,MATCH($C4,Takeoff_In!$A$2:$A$300,0)))) | I4: =IF($C4="",0,IF(AND(ISNUMBER($F4),$F4>0),G4/$F4,NA())) | J4: =IF($C4="",0,IF(AND(ISNUMBER($F4),$F4>0),H4/$F4,NA())) | K4: =IF($C4="",0,INDEX(Crews!$H$2:$H$20,MATCH($E4,Crews!$A$2:$A$20,0))) | L4: =IF($C4="",0,I4*K4) | M4: =IF($C4="",0,J4*K4) | N4: =IF($C4="",0,IF(G4=0,0,L4/G4)) | P4: standard
A5: L04 | B5: Install top rail and brace rail | C5: D06 | D5: =IF($C5="","",INDEX(Takeoff_In!$C$2:$C$300,MATCH($C5,Takeoff_In!$A$2:$A$300,0))) | E5: CR2 | F5: 90 | G5: =IF($C5="","",IF(INDEX(Takeoff_In!$D$2:$D$300,MATCH($C5,Takeoff_In!$A$2:$A$300,0))="",NA(),INDEX(Takeoff_In!$D$2:$D$300,MATCH($C5,Takeoff_In!$A$2:$A$300,0)))) | H5: =IF($C5="","",IF(INDEX(Takeoff_In!$E$2:$E$300,MATCH($C5,Takeoff_In!$A$2:$A$300,0))="",NA(),INDEX(Takeoff_In!$E$2:$E$300,MATCH($C5,Takeoff_In!$A$2:$A$300,0)))) | I5: =IF($C5="",0,IF(AND(ISNUMBER($F5),$F5>0),G5/$F5,NA())) | J5: =IF($C5="",0,IF(AND(ISNUMBER($F5),$F5>0),H5/$F5,NA())) | K5: =IF($C5="",0,INDEX(Crews!$H$2:$H$20,MATCH($E5,Crews!$A$2:$A$20,0))) | L5: =IF($C5="",0,I5*K5) | M5: =IF($C5="",0,J5*K5) | N5: =IF($C5="",0,IF(G5=0,0,L5/G5)) | P5: standard
A6: L05 | B6: Install braces and truss rods | C6: D08 | D6: =IF($C6="","",INDEX(Takeoff_In!$C$2:$C$300,MATCH($C6,Takeoff_In!$A$2:$A$300,0))) | E6: CR2 | F6: 3 | G6: =IF($C6="","",IF(INDEX(Takeoff_In!$D$2:$D$300,MATCH($C6,Takeoff_In!$A$2:$A$300,0))="",NA(),INDEX(Takeoff_In!$D$2:$D$300,MATCH($C6,Takeoff_In!$A$2:$A$300,0)))) | H6: =IF($C6="","",IF(INDEX(Takeoff_In!$E$2:$E$300,MATCH($C6,Takeoff_In!$A$2:$A$300,0))="",NA(),INDEX(Takeoff_In!$E$2:$E$300,MATCH($C6,Takeoff_In!$A$2:$A$300,0)))) | I6: =IF($C6="",0,IF(AND(ISNUMBER($F6),$F6>0),G6/$F6,NA())) | J6: =IF($C6="",0,IF(AND(ISNUMBER($F6),$F6>0),H6/$F6,NA())) | K6: =IF($C6="",0,INDEX(Crews!$H$2:$H$20,MATCH($E6,Crews!$A$2:$A$20,0))) | L6: =IF($C6="",0,I6*K6) | M6: =IF($C6="",0,J6*K6) | N6: =IF($C6="",0,IF(G6=0,0,L6/G6)) | P6: standard
A7: L06 | B7: Hang and tension fabric | C7: D07 | D7: =IF($C7="","",INDEX(Takeoff_In!$C$2:$C$300,MATCH($C7,Takeoff_In!$A$2:$A$300,0))) | E7: CR3 | F7: 35 | G7: =IF($C7="","",IF(INDEX(Takeoff_In!$D$2:$D$300,MATCH($C7,Takeoff_In!$A$2:$A$300,0))="",NA(),INDEX(Takeoff_In!$D$2:$D$300,MATCH($C7,Takeoff_In!$A$2:$A$300,0)))) | H7: =IF($C7="","",IF(INDEX(Takeoff_In!$E$2:$E$300,MATCH($C7,Takeoff_In!$A$2:$A$300,0))="",NA(),INDEX(Takeoff_In!$E$2:$E$300,MATCH($C7,Takeoff_In!$A$2:$A$300,0)))) | I7: =IF($C7="",0,IF(AND(ISNUMBER($F7),$F7>0),G7/$F7,NA())) | J7: =IF($C7="",0,IF(AND(ISNUMBER($F7),$F7>0),H7/$F7,NA())) | K7: =IF($C7="",0,INDEX(Crews!$H$2:$H$20,MATCH($E7,Crews!$A$2:$A$20,0))) | L7: =IF($C7="",0,I7*K7) | M7: =IF($C7="",0,J7*K7) | N7: =IF($C7="",0,IF(G7=0,0,L7/G7)) | P7: standard
A8: L07 | B8: Install bottom tension wire | C8: D11 | D8: =IF($C8="","",INDEX(Takeoff_In!$C$2:$C$300,MATCH($C8,Takeoff_In!$A$2:$A$300,0))) | E8: CR3 | F8: 80 | G8: =IF($C8="","",IF(INDEX(Takeoff_In!$D$2:$D$300,MATCH($C8,Takeoff_In!$A$2:$A$300,0))="",NA(),INDEX(Takeoff_In!$D$2:$D$300,MATCH($C8,Takeoff_In!$A$2:$A$300,0)))) | H8: =IF($C8="","",IF(INDEX(Takeoff_In!$E$2:$E$300,MATCH($C8,Takeoff_In!$A$2:$A$300,0))="",NA(),INDEX(Takeoff_In!$E$2:$E$300,MATCH($C8,Takeoff_In!$A$2:$A$300,0)))) | I8: =IF($C8="",0,IF(AND(ISNUMBER($F8),$F8>0),G8/$F8,NA())) | J8: =IF($C8="",0,IF(AND(ISNUMBER($F8),$F8>0),H8/$F8,NA())) | K8: =IF($C8="",0,INDEX(Crews!$H$2:$H$20,MATCH($E8,Crews!$A$2:$A$20,0))) | L8: =IF($C8="",0,I8*K8) | M8: =IF($C8="",0,J8*K8) | N8: =IF($C8="",0,IF(G8=0,0,L8/G8)) | P8: standard
A9: L08 | B9: Hang gates and hardware | C9: D09 | D9: =IF($C9="","",INDEX(Takeoff_In!$C$2:$C$300,MATCH($C9,Takeoff_In!$A$2:$A$300,0))) | E9: CR3 | F9: 0.5 | G9: =IF($C9="","",IF(INDEX(Takeoff_In!$D$2:$D$300,MATCH($C9,Takeoff_In!$A$2:$A$300,0))="",NA(),INDEX(Takeoff_In!$D$2:$D$300,MATCH($C9,Takeoff_In!$A$2:$A$300,0)))) | H9: =IF($C9="","",IF(INDEX(Takeoff_In!$E$2:$E$300,MATCH($C9,Takeoff_In!$A$2:$A$300,0))="",NA(),INDEX(Takeoff_In!$E$2:$E$300,MATCH($C9,Takeoff_In!$A$2:$A$300,0)))) | I9: =IF($C9="",0,IF(AND(ISNUMBER($F9),$F9>0),G9/$F9,NA())) | J9: =IF($C9="",0,IF(AND(ISNUMBER($F9),$F9>0),H9/$F9,NA())) | K9: =IF($C9="",0,INDEX(Crews!$H$2:$H$20,MATCH($E9,Crews!$A$2:$A$20,0))) | L9: =IF($C9="",0,I9*K9) | M9: =IF($C9="",0,J9*K9) | N9: =IF($C9="",0,IF(G9=0,0,L9/G9)) | P9: standard
A10: L09 | B10: Install windscreen | C10: D10 | D10: =IF($C10="","",INDEX(Takeoff_In!$C$2:$C$300,MATCH($C10,Takeoff_In!$A$2:$A$300,0))) | E10: CR4 | F10: 40 | G10: =IF($C10="","",IF(INDEX(Takeoff_In!$D$2:$D$300,MATCH($C10,Takeoff_In!$A$2:$A$300,0))="",NA(),INDEX(Takeoff_In!$D$2:$D$300,MATCH($C10,Takeoff_In!$A$2:$A$300,0)))) | H10: =IF($C10="","",IF(INDEX(Takeoff_In!$E$2:$E$300,MATCH($C10,Takeoff_In!$A$2:$A$300,0))="",NA(),INDEX(Takeoff_In!$E$2:$E$300,MATCH($C10,Takeoff_In!$A$2:$A$300,0)))) | I10: =IF($C10="",0,IF(AND(ISNUMBER($F10),$F10>0),G10/$F10,NA())) | J10: =IF($C10="",0,IF(AND(ISNUMBER($F10),$F10>0),H10/$F10,NA())) | K10: =IF($C10="",0,INDEX(Crews!$H$2:$H$20,MATCH($E10,Crews!$A$2:$A$20,0))) | L10: =IF($C10="",0,I10*K10) | M10: =IF($C10="",0,J10*K10) | N10: =IF($C10="",0,IF(G10=0,0,L10/G10)) | P10: standard
A11: L10 | B11: Cleanup and spoils haul | C11: D12 | D11: =IF($C11="","",INDEX(Takeoff_In!$C$2:$C$300,MATCH($C11,Takeoff_In!$A$2:$A$300,0))) | E11: CR4 | F11: 200 | G11: =IF($C11="","",IF(INDEX(Takeoff_In!$D$2:$D$300,MATCH($C11,Takeoff_In!$A$2:$A$300,0))="",NA(),INDEX(Takeoff_In!$D$2:$D$300,MATCH($C11,Takeoff_In!$A$2:$A$300,0)))) | H11: =IF($C11="","",IF(INDEX(Takeoff_In!$E$2:$E$300,MATCH($C11,Takeoff_In!$A$2:$A$300,0))="",NA(),INDEX(Takeoff_In!$E$2:$E$300,MATCH($C11,Takeoff_In!$A$2:$A$300,0)))) | I11: =IF($C11="",0,IF(AND(ISNUMBER($F11),$F11>0),G11/$F11,NA())) | J11: =IF($C11="",0,IF(AND(ISNUMBER($F11),$F11>0),H11/$F11,NA())) | K11: =IF($C11="",0,INDEX(Crews!$H$2:$H$20,MATCH($E11,Crews!$A$2:$A$20,0))) | L11: =IF($C11="",0,I11*K11) | M11: =IF($C11="",0,J11*K11) | N11: =IF($C11="",0,IF(G11=0,0,L11/G11)) | P11: standard
D12: =IF($C12="","",INDEX(Takeoff_In!$C$2:$C$300,MATCH($C12,Takeoff_In!$A$2:$A$300,0))) | G12: =IF($C12="","",IF(INDEX(Takeoff_In!$D$2:$D$300,MATCH($C12,Takeoff_In!$A$2:$A$300,0))="",NA(),INDEX(Takeoff_In!$D$2:$D$300,MATCH($C12,Takeoff_In!$A$2:$A$300,0)))) | H12: =IF($C12="","",IF(INDEX(Takeoff_In!$E$2:$E$300,MATCH($C12,Takeoff_In!$A$2:$A$300,0))="",NA(),INDEX(Takeoff_In!$E$2:$E$300,MATCH($C12,Takeoff_In!$A$2:$A$300,0)))) | I12: =IF($C12="",0,IF(AND(ISNUMBER($F12),$F12>0),G12/$F12,NA())) | J12: =IF($C12="",0,IF(AND(ISNUMBER($F12),$F12>0),H12/$F12,NA())) | K12: =IF($C12="",0,INDEX(Crews!$H$2:$H$20,MATCH($E12,Crews!$A$2:$A$20,0))) | L12: =IF($C12="",0,I12*K12) | M12: =IF($C12="",0,J12*K12) | N12: =IF($C12="",0,IF(G12=0,0,L12/G12))
D13: =IF($C13="","",INDEX(Takeoff_In!$C$2:$C$300,MATCH($C13,Takeoff_In!$A$2:$A$300,0))) | G13: =IF($C13="","",IF(INDEX(Takeoff_In!$D$2:$D$300,MATCH($C13,Takeoff_In!$A$2:$A$300,0))="",NA(),INDEX(Takeoff_In!$D$2:$D$300,MATCH($C13,Takeoff_In!$A$2:$A$300,0)))) | H13: =IF($C13="","",IF(INDEX(Takeoff_In!$E$2:$E$300,MATCH($C13,Takeoff_In!$A$2:$A$300,0))="",NA(),INDEX(Takeoff_In!$E$2:$E$300,MATCH($C13,Takeoff_In!$A$2:$A$300,0)))) | I13: =IF($C13="",0,IF(AND(ISNUMBER($F13),$F13>0),G13/$F13,NA())) | J13: =IF($C13="",0,IF(AND(ISNUMBER($F13),$F13>0),H13/$F13,NA())) | K13: =IF($C13="",0,INDEX(Crews!$H$2:$H$20,MATCH($E13,Crews!$A$2:$A$20,0))) | L13: =IF($C13="",0,I13*K13) | M13: =IF($C13="",0,J13*K13) | N13: =IF($C13="",0,IF(G13=0,0,L13/G13))
D14: =IF($C14="","",INDEX(Takeoff_In!$C$2:$C$300,MATCH($C14,Takeoff_In!$A$2:$A$300,0))) | G14: =IF($C14="","",IF(INDEX(Takeoff_In!$D$2:$D$300,MATCH($C14,Takeoff_In!$A$2:$A$300,0))="",NA(),INDEX(Takeoff_In!$D$2:$D$300,MATCH($C14,Takeoff_In!$A$2:$A$300,0)))) | H14: =IF($C14="","",IF(INDEX(Takeoff_In!$E$2:$E$300,MATCH($C14,Takeoff_In!$A$2:$A$300,0))="",NA(),INDEX(Takeoff_In!$E$2:$E$300,MATCH($C14,Takeoff_In!$A$2:$A$300,0)))) | I14: =IF($C14="",0,IF(AND(ISNUMBER($F14),$F14>0),G14/$F14,NA())) | J14: =IF($C14="",0,IF(AND(ISNUMBER($F14),$F14>0),H14/$F14,NA())) | K14: =IF($C14="",0,INDEX(Crews!$H$2:$H$20,MATCH($E14,Crews!$A$2:$A$20,0))) | L14: =IF($C14="",0,I14*K14) | M14: =IF($C14="",0,J14*K14) | N14: =IF($C14="",0,IF(G14=0,0,L14/G14))
D15: =IF($C15="","",INDEX(Takeoff_In!$C$2:$C$300,MATCH($C15,Takeoff_In!$A$2:$A$300,0))) | G15: =IF($C15="","",IF(INDEX(Takeoff_In!$D$2:$D$300,MATCH($C15,Takeoff_In!$A$2:$A$300,0))="",NA(),INDEX(Takeoff_In!$D$2:$D$300,MATCH($C15,Takeoff_In!$A$2:$A$300,0)))) | H15: =IF($C15="","",IF(INDEX(Takeoff_In!$E$2:$E$300,MATCH($C15,Takeoff_In!$A$2:$A$300,0))="",NA(),INDEX(Takeoff_In!$E$2:$E$300,MATCH($C15,Takeoff_In!$A$2:$A$300,0)))) | I15: =IF($C15="",0,IF(AND(ISNUMBER($F15),$F15>0),G15/$F15,NA())) | J15: =IF($C15="",0,IF(AND(ISNUMBER($F15),$F15>0),H15/$F15,NA())) | K15: =IF($C15="",0,INDEX(Crews!$H$2:$H$20,MATCH($E15,Crews!$A$2:$A$20,0))) | L15: =IF($C15="",0,I15*K15) | M15: =IF($C15="",0,J15*K15) | N15: =IF($C15="",0,IF(G15=0,0,L15/G15))
D16: =IF($C16="","",INDEX(Takeoff_In!$C$2:$C$300,MATCH($C16,Takeoff_In!$A$2:$A$300,0))) | G16: =IF($C16="","",IF(INDEX(Takeoff_In!$D$2:$D$300,MATCH($C16,Takeoff_In!$A$2:$A$300,0))="",NA(),INDEX(Takeoff_In!$D$2:$D$300,MATCH($C16,Takeoff_In!$A$2:$A$300,0)))) | H16: =IF($C16="","",IF(INDEX(Takeoff_In!$E$2:$E$300,MATCH($C16,Takeoff_In!$A$2:$A$300,0))="",NA(),INDEX(Takeoff_In!$E$2:$E$300,MATCH($C16,Takeoff_In!$A$2:$A$300,0)))) | I16: =IF($C16="",0,IF(AND(ISNUMBER($F16),$F16>0),G16/$F16,NA())) | J16: =IF($C16="",0,IF(AND(ISNUMBER($F16),$F16>0),H16/$F16,NA())) | K16: =IF($C16="",0,INDEX(Crews!$H$2:$H$20,MATCH($E16,Crews!$A$2:$A$20,0))) | L16: =IF($C16="",0,I16*K16) | M16: =IF($C16="",0,J16*K16) | N16: =IF($C16="",0,IF(G16=0,0,L16/G16))
D17: =IF($C17="","",INDEX(Takeoff_In!$C$2:$C$300,MATCH($C17,Takeoff_In!$A$2:$A$300,0))) | G17: =IF($C17="","",IF(INDEX(Takeoff_In!$D$2:$D$300,MATCH($C17,Takeoff_In!$A$2:$A$300,0))="",NA(),INDEX(Takeoff_In!$D$2:$D$300,MATCH($C17,Takeoff_In!$A$2:$A$300,0)))) | H17: =IF($C17="","",IF(INDEX(Takeoff_In!$E$2:$E$300,MATCH($C17,Takeoff_In!$A$2:$A$300,0))="",NA(),INDEX(Takeoff_In!$E$2:$E$300,MATCH($C17,Takeoff_In!$A$2:$A$300,0)))) | I17: =IF($C17="",0,IF(AND(ISNUMBER($F17),$F17>0),G17/$F17,NA())) | J17: =IF($C17="",0,IF(AND(ISNUMBER($F17),$F17>0),H17/$F17,NA())) | K17: =IF($C17="",0,INDEX(Crews!$H$2:$H$20,MATCH($E17,Crews!$A$2:$A$20,0))) | L17: =IF($C17="",0,I17*K17) | M17: =IF($C17="",0,J17*K17) | N17: =IF($C17="",0,IF(G17=0,0,L17/G17))
D18: =IF($C18="","",INDEX(Takeoff_In!$C$2:$C$300,MATCH($C18,Takeoff_In!$A$2:$A$300,0))) | G18: =IF($C18="","",IF(INDEX(Takeoff_In!$D$2:$D$300,MATCH($C18,Takeoff_In!$A$2:$A$300,0))="",NA(),INDEX(Takeoff_In!$D$2:$D$300,MATCH($C18,Takeoff_In!$A$2:$A$300,0)))) | H18: =IF($C18="","",IF(INDEX(Takeoff_In!$E$2:$E$300,MATCH($C18,Takeoff_In!$A$2:$A$300,0))="",NA(),INDEX(Takeoff_In!$E$2:$E$300,MATCH($C18,Takeoff_In!$A$2:$A$300,0)))) | I18: =IF($C18="",0,IF(AND(ISNUMBER($F18),$F18>0),G18/$F18,NA())) | J18: =IF($C18="",0,IF(AND(ISNUMBER($F18),$F18>0),H18/$F18,NA())) | K18: =IF($C18="",0,INDEX(Crews!$H$2:$H$20,MATCH($E18,Crews!$A$2:$A$20,0))) | L18: =IF($C18="",0,I18*K18) | M18: =IF($C18="",0,J18*K18) | N18: =IF($C18="",0,IF(G18=0,0,L18/G18))
D19: =IF($C19="","",INDEX(Takeoff_In!$C$2:$C$300,MATCH($C19,Takeoff_In!$A$2:$A$300,0))) | G19: =IF($C19="","",IF(INDEX(Takeoff_In!$D$2:$D$300,MATCH($C19,Takeoff_In!$A$2:$A$300,0))="",NA(),INDEX(Takeoff_In!$D$2:$D$300,MATCH($C19,Takeoff_In!$A$2:$A$300,0)))) | H19: =IF($C19="","",IF(INDEX(Takeoff_In!$E$2:$E$300,MATCH($C19,Takeoff_In!$A$2:$A$300,0))="",NA(),INDEX(Takeoff_In!$E$2:$E$300,MATCH($C19,Takeoff_In!$A$2:$A$300,0)))) | I19: =IF($C19="",0,IF(AND(ISNUMBER($F19),$F19>0),G19/$F19,NA())) | J19: =IF($C19="",0,IF(AND(ISNUMBER($F19),$F19>0),H19/$F19,NA())) | K19: =IF($C19="",0,INDEX(Crews!$H$2:$H$20,MATCH($E19,Crews!$A$2:$A$20,0))) | L19: =IF($C19="",0,I19*K19) | M19: =IF($C19="",0,J19*K19) | N19: =IF($C19="",0,IF(G19=0,0,L19/G19))
D20: =IF($C20="","",INDEX(Takeoff_In!$C$2:$C$300,MATCH($C20,Takeoff_In!$A$2:$A$300,0))) | G20: =IF($C20="","",IF(INDEX(Takeoff_In!$D$2:$D$300,MATCH($C20,Takeoff_In!$A$2:$A$300,0))="",NA(),INDEX(Takeoff_In!$D$2:$D$300,MATCH($C20,Takeoff_In!$A$2:$A$300,0)))) | H20: =IF($C20="","",IF(INDEX(Takeoff_In!$E$2:$E$300,MATCH($C20,Takeoff_In!$A$2:$A$300,0))="",NA(),INDEX(Takeoff_In!$E$2:$E$300,MATCH($C20,Takeoff_In!$A$2:$A$300,0)))) | I20: =IF($C20="",0,IF(AND(ISNUMBER($F20),$F20>0),G20/$F20,NA())) | J20: =IF($C20="",0,IF(AND(ISNUMBER($F20),$F20>0),H20/$F20,NA())) | K20: =IF($C20="",0,INDEX(Crews!$H$2:$H$20,MATCH($E20,Crews!$A$2:$A$20,0))) | L20: =IF($C20="",0,I20*K20) | M20: =IF($C20="",0,J20*K20) | N20: =IF($C20="",0,IF(G20=0,0,L20/G20))
D21: =IF($C21="","",INDEX(Takeoff_In!$C$2:$C$300,MATCH($C21,Takeoff_In!$A$2:$A$300,0))) | G21: =IF($C21="","",IF(INDEX(Takeoff_In!$D$2:$D$300,MATCH($C21,Takeoff_In!$A$2:$A$300,0))="",NA(),INDEX(Takeoff_In!$D$2:$D$300,MATCH($C21,Takeoff_In!$A$2:$A$300,0)))) | H21: =IF($C21="","",IF(INDEX(Takeoff_In!$E$2:$E$300,MATCH($C21,Takeoff_In!$A$2:$A$300,0))="",NA(),INDEX(Takeoff_In!$E$2:$E$300,MATCH($C21,Takeoff_In!$A$2:$A$300,0)))) | I21: =IF($C21="",0,IF(AND(ISNUMBER($F21),$F21>0),G21/$F21,NA())) | J21: =IF($C21="",0,IF(AND(ISNUMBER($F21),$F21>0),H21/$F21,NA())) | K21: =IF($C21="",0,INDEX(Crews!$H$2:$H$20,MATCH($E21,Crews!$A$2:$A$20,0))) | L21: =IF($C21="",0,I21*K21) | M21: =IF($C21="",0,J21*K21) | N21: =IF($C21="",0,IF(G21=0,0,L21/G21))
D22: =IF($C22="","",INDEX(Takeoff_In!$C$2:$C$300,MATCH($C22,Takeoff_In!$A$2:$A$300,0))) | G22: =IF($C22="","",IF(INDEX(Takeoff_In!$D$2:$D$300,MATCH($C22,Takeoff_In!$A$2:$A$300,0))="",NA(),INDEX(Takeoff_In!$D$2:$D$300,MATCH($C22,Takeoff_In!$A$2:$A$300,0)))) | H22: =IF($C22="","",IF(INDEX(Takeoff_In!$E$2:$E$300,MATCH($C22,Takeoff_In!$A$2:$A$300,0))="",NA(),INDEX(Takeoff_In!$E$2:$E$300,MATCH($C22,Takeoff_In!$A$2:$A$300,0)))) | I22: =IF($C22="",0,IF(AND(ISNUMBER($F22),$F22>0),G22/$F22,NA())) | J22: =IF($C22="",0,IF(AND(ISNUMBER($F22),$F22>0),H22/$F22,NA())) | K22: =IF($C22="",0,INDEX(Crews!$H$2:$H$20,MATCH($E22,Crews!$A$2:$A$20,0))) | L22: =IF($C22="",0,I22*K22) | M22: =IF($C22="",0,J22*K22) | N22: =IF($C22="",0,IF(G22=0,0,L22/G22))
D23: =IF($C23="","",INDEX(Takeoff_In!$C$2:$C$300,MATCH($C23,Takeoff_In!$A$2:$A$300,0))) | G23: =IF($C23="","",IF(INDEX(Takeoff_In!$D$2:$D$300,MATCH($C23,Takeoff_In!$A$2:$A$300,0))="",NA(),INDEX(Takeoff_In!$D$2:$D$300,MATCH($C23,Takeoff_In!$A$2:$A$300,0)))) | H23: =IF($C23="","",IF(INDEX(Takeoff_In!$E$2:$E$300,MATCH($C23,Takeoff_In!$A$2:$A$300,0))="",NA(),INDEX(Takeoff_In!$E$2:$E$300,MATCH($C23,Takeoff_In!$A$2:$A$300,0)))) | I23: =IF($C23="",0,IF(AND(ISNUMBER($F23),$F23>0),G23/$F23,NA())) | J23: =IF($C23="",0,IF(AND(ISNUMBER($F23),$F23>0),H23/$F23,NA())) | K23: =IF($C23="",0,INDEX(Crews!$H$2:$H$20,MATCH($E23,Crews!$A$2:$A$20,0))) | L23: =IF($C23="",0,I23*K23) | M23: =IF($C23="",0,J23*K23) | N23: =IF($C23="",0,IF(G23=0,0,L23/G23))
... D60: =IF($C60="","",INDEX(Takeoff_In!$C$2:$C$300,MATCH($C60,Takeoff_In!$A$2:$A$300,0))) | G60: =IF($C60="","",IF(INDEX(Takeoff_In!$D$2:$D$300,MATCH($C60,Takeoff_In!$A$2:$A$300,0))="",NA(),INDEX(Takeoff_In!$D$2:$D$300,MATCH($C60,Takeoff_In!$A$2:$A$300,0)))) | H60: =IF($C60="","",IF(INDEX(Takeoff_In!$E$2:$E$300,MATCH($C60,Takeoff_In!$A$2:$A$300,0))="",NA(),INDEX(Takeoff_In!$E$2:$E$300,MATCH($C60,Takeoff_In!$A$2:$A$300,0)))) | I60: =IF($C60="",0,IF(AND(ISNUMBER($F60),$F60>0),G60/$F60,NA())) | J60: =IF($C60="",0,IF(AND(ISNUMBER($F60),$F60>0),H60/$F60,NA())) | K60: =IF($C60="",0,INDEX(Crews!$H$2:$H$20,MATCH($E60,Crews!$A$2:$A$20,0))) | L60: =IF($C60="",0,I60*K60) | M60: =IF($C60="",0,J60*K60) | N60: =IF($C60="",0,IF(G60=0,0,L60/G60))

Sheet Crew_Production
A1: task_id | B1: crew_id | C1: production_rate | D1: rate_basis | E1: notes
A2: L01 | B2: CR11 | C2: 150 | D2: standard | E2: Fictional baseline production for this crew; efficiency is applied separately.
A3: L02 | B3: CR11 | C3: 7.2 | D3: standard | E3: Fictional baseline production for this crew; efficiency is applied separately.
A4: L03 | B4: CR11 | C4: 5.1 | D4: standard | E4: Fictional baseline production for this crew; efficiency is applied separately.
A5: L04 | B5: CR11 | C5: 81 | D5: standard | E5: Fictional baseline production for this crew; efficiency is applied separately.
A6: L05 | B6: CR11 | C6: 2.4 | D6: standard | E6: Fictional baseline production for this crew; efficiency is applied separately.
A7: L06 | B7: CR11 | C7: 36.75 | D7: standard | E7: Fictional baseline production for this crew; efficiency is applied separately.
A8: L07 | B8: CR11 | C8: 88 | D8: standard | E8: Fictional baseline production for this crew; efficiency is applied separately.
A9: L08 | B9: CR11 | C9: 0.35 | D9: standard | E9: Fictional baseline production for this crew; efficiency is applied separately.
A10: L09 | B10: CR11 | C10: 44 | D10: standard | E10: Fictional baseline production for this crew; efficiency is applied separately.
A11: L10 | B11: CR11 | C11: 230 | D11: standard | E11: Fictional baseline production for this crew; efficiency is applied separately.
A12: L01 | B12: CR12 | C12: 150 | D12: standard | E12: Fictional baseline production for this crew; efficiency is applied separately.
A13: L02 | B13: CR12 | C13: 7.6 | D13: standard | E13: Fictional baseline production for this crew; efficiency is applied separately.
... A41: L10 | B41: CR14 | C41: 196 | D41: standard | E41: Fictional baseline production for this crew; efficiency is applied separately.

Sheet Equipment
A1: equip_id | B1: equipment | C1: owned_or_rented | D1: basis (day/hr/week/each) | E1: rate | F1: days_or_units_base | G1: days_or_units_alt | H1: fuel_and_consumables_base | I1: fuel_and_consumables_alt | J1: delivery_pickup_each | K1: delivery_trips | L1: ext_base | M1: ext_alt | N1: notes
A2: E01 | B2: Skid steer with auger | C2: rented | D2: day | E2: 302 | F2: 2 | G2: 2 | H2: 40 | I2: 40 | J2: 0 | K2: 0 | L2: =IF($B2="",0,IF(AND($E2="",$F2="",$G2=""),0,IF(AND(ISNUMBER($E2),ISNUMBER(F2),ISNUMBER(H2),ISNUMBER($J2),ISNUMBER($K2)),$E2*F2+H2+$J2*$K2,NA()))) | M2: =IF($B2="",0,IF(AND($E2="",$F2="",$G2=""),0,IF(AND(ISNUMBER($E2),ISNUMBER(G2),ISNUMBER(I2),ISNUMBER($J2),ISNUMBER($K2)),$E2*G2+I2+$J2*$K2,NA()))) | N2: Fictional reference estimate; not a vendor quote.
A3: E02 | B3: Post driver | L3: =IF($B3="",0,IF(AND($E3="",$F3="",$G3=""),0,IF(AND(ISNUMBER($E3),ISNUMBER(F3),ISNUMBER(H3),ISNUMBER($J3),ISNUMBER($K3)),$E3*F3+H3+$J3*$K3,NA()))) | M3: =IF($B3="",0,IF(AND($E3="",$F3="",$G3=""),0,IF(AND(ISNUMBER($E3),ISNUMBER(G3),ISNUMBER(I3),ISNUMBER($J3),ISNUMBER($K3)),$E3*G3+I3+$J3*$K3,NA())))
A4: E03 | B4: Mini excavator | L4: =IF($B4="",0,IF(AND($E4="",$F4="",$G4=""),0,IF(AND(ISNUMBER($E4),ISNUMBER(F4),ISNUMBER(H4),ISNUMBER($J4),ISNUMBER($K4)),$E4*F4+H4+$J4*$K4,NA()))) | M4: =IF($B4="",0,IF(AND($E4="",$F4="",$G4=""),0,IF(AND(ISNUMBER($E4),ISNUMBER(G4),ISNUMBER(I4),ISNUMBER($J4),ISNUMBER($K4)),$E4*G4+I4+$J4*$K4,NA())))
A5: E04 | B5: Concrete mixer / mixer truck | L5: =IF($B5="",0,IF(AND($E5="",$F5="",$G5=""),0,IF(AND(ISNUMBER($E5),ISNUMBER(F5),ISNUMBER(H5),ISNUMBER($J5),ISNUMBER($K5)),$E5*F5+H5+$J5*$K5,NA()))) | M5: =IF($B5="",0,IF(AND($E5="",$F5="",$G5=""),0,IF(AND(ISNUMBER($E5),ISNUMBER(G5),ISNUMBER(I5),ISNUMBER($J5),ISNUMBER($K5)),$E5*G5+I5+$J5*$K5,NA())))
A6: E05 | B6: Pickup truck | C6: owned | D6: day | E6: 85 | F6: 11 | G6: 9 | H6: 35 | I6: 28 | J6: 0 | K6: 0 | L6: =IF($B6="",0,IF(AND($E6="",$F6="",$G6=""),0,IF(AND(ISNUMBER($E6),ISNUMBER(F6),ISNUMBER(H6),ISNUMBER($J6),ISNUMBER($K6)),$E6*F6+H6+$J6*$K6,NA()))) | M6: =IF($B6="",0,IF(AND($E6="",$F6="",$G6=""),0,IF(AND(ISNUMBER($E6),ISNUMBER(G6),ISNUMBER(I6),ISNUMBER($J6),ISNUMBER($K6)),$E6*G6+I6+$J6*$K6,NA()))) | N6: Pickup. Owned-cost allowance, estimate. Fuel for the job.
A7: E06 | B7: Equipment trailer | C7: owned | D7: day | E7: 35 | F7: 11 | G7: 9 | H7: 0 | I7: 0 | J7: 0 | K7: 0 | L7: =IF($B7="",0,IF(AND($E7="",$F7="",$G7=""),0,IF(AND(ISNUMBER($E7),ISNUMBER(F7),ISNUMBER(H7),ISNUMBER($J7),ISNUMBER($K7)),$E7*F7+H7+$J7*$K7,NA()))) | M7: =IF($B7="",0,IF(AND($E7="",$F7="",$G7=""),0,IF(AND(ISNUMBER($E7),ISNUMBER(G7),ISNUMBER(I7),ISNUMBER($J7),ISNUMBER($K7)),$E7*G7+I7+$J7*$K7,NA()))) | N7: Trailer allowance, estimate.
A8: E07 | B8: Generator | L8: =IF($B8="",0,IF(AND($E8="",$F8="",$G8=""),0,IF(AND(ISNUMBER($E8),ISNUMBER(F8),ISNUMBER(H8),ISNUMBER($J8),ISNUMBER($K8)),$E8*F8+H8+$J8*$K8,NA()))) | M8: =IF($B8="",0,IF(AND($E8="",$F8="",$G8=""),0,IF(AND(ISNUMBER($E8),ISNUMBER(G8),ISNUMBER(I8),ISNUMBER($J8),ISNUMBER($K8)),$E8*G8+I8+$J8*$K8,NA())))
A9: E08 | B9: Laser level / layout tools | C9: owned | D9: day | E9: 25 | F9: 3 | G9: 3 | H9: 0 | I9: 0 | J9: 0 | K9: 0 | L9: =IF($B9="",0,IF(AND($E9="",$F9="",$G9=""),0,IF(AND(ISNUMBER($E9),ISNUMBER(F9),ISNUMBER(H9),ISNUMBER($J9),ISNUMBER($K9)),$E9*F9+H9+$J9*$K9,NA()))) | M9: =IF($B9="",0,IF(AND($E9="",$F9="",$G9=""),0,IF(AND(ISNUMBER($E9),ISNUMBER(G9),ISNUMBER(I9),ISNUMBER($J9),ISNUMBER($K9)),$E9*G9+I9+$J9*$K9,NA()))) | N9: Laser level and layout tools, allowance.
A10: E09 | B10: Fabric stretcher / come-alongs | C10: owned | D10: day | E10: 20 | F10: 6 | G10: 5 | H10: 0 | I10: 0 | J10: 0 | K10: 0 | L10: =IF($B10="",0,IF(AND($E10="",$F10="",$G10=""),0,IF(AND(ISNUMBER($E10),ISNUMBER(F10),ISNUMBER(H10),ISNUMBER($J10),ISNUMBER($K10)),$E10*F10+H10+$J10*$K10,NA()))) | M10: =IF($B10="",0,IF(AND($E10="",$F10="",$G10=""),0,IF(AND(ISNUMBER($E10),ISNUMBER(G10),ISNUMBER(I10),ISNUMBER($J10),ISNUMBER($K10)),$E10*G10+I10+$J10*$K10,NA()))) | N10: Fabric stretchers / come-alongs allowance.
A11: E10 | B11: Hand tools and consumables | C11: owned | D11: day | E11: 40 | F11: 11 | G11: 9 | H11: 0 | I11: 0 | J11: 0 | K11: 0 | L11: =IF($B11="",0,IF(AND($E11="",$F11="",$G11=""),0,IF(AND(ISNUMBER($E11),ISNUMBER(F11),ISNUMBER(H11),ISNUMBER($J11),ISNUMBER($K11)),$E11*F11+H11+$J11*$K11,NA()))) | M11: =IF($B11="",0,IF(AND($E11="",$F11="",$G11=""),0,IF(AND(ISNUMBER($E11),ISNUMBER(G11),ISNUMBER(I11),ISNUMBER($J11),ISNUMBER($K11)),$E11*G11+I11+$J11*$K11,NA()))) | N11: Hand tools and consumables allowance.
A12: E11 | B12: Rental: ______ | L12: =IF($B12="",0,IF(AND($E12="",$F12="",$G12=""),0,IF(AND(ISNUMBER($E12),ISNUMBER(F12),ISNUMBER(H12),ISNUMBER($J12),ISNUMBER($K12)),$E12*F12+H12+$J12*$K12,NA()))) | M12: =IF($B12="",0,IF(AND($E12="",$F12="",$G12=""),0,IF(AND(ISNUMBER($E12),ISNUMBER(G12),ISNUMBER(I12),ISNUMBER($J12),ISNUMBER($K12)),$E12*G12+I12+$J12*$K12,NA())))
A13: E12 | B13: Rental: ______ | L13: =IF($B13="",0,IF(AND($E13="",$F13="",$G13=""),0,IF(AND(ISNUMBER($E13),ISNUMBER(F13),ISNUMBER(H13),ISNUMBER($J13),ISNUMBER($K13)),$E13*F13+H13+$J13*$K13,NA()))) | M13: =IF($B13="",0,IF(AND($E13="",$F13="",$G13=""),0,IF(AND(ISNUMBER($E13),ISNUMBER(G13),ISNUMBER(I13),ISNUMBER($J13),ISNUMBER($K13)),$E13*G13+I13+$J13*$K13,NA())))
L14: =IF($B14="",0,IF(AND($E14="",$F14="",$G14=""),0,IF(AND(ISNUMBER($E14),ISNUMBER(F14),ISNUMBER(H14),ISNUMBER($J14),ISNUMBER($K14)),$E14*F14+H14+$J14*$K14,NA()))) | M14: =IF($B14="",0,IF(AND($E14="",$F14="",$G14=""),0,IF(AND(ISNUMBER($E14),ISNUMBER(G14),ISNUMBER(I14),ISNUMBER($J14),ISNUMBER($K14)),$E14*G14+I14+$J14*$K14,NA())))
L15: =IF($B15="",0,IF(AND($E15="",$F15="",$G15=""),0,IF(AND(ISNUMBER($E15),ISNUMBER(F15),ISNUMBER(H15),ISNUMBER($J15),ISNUMBER($K15)),$E15*F15+H15+$J15*$K15,NA()))) | M15: =IF($B15="",0,IF(AND($E15="",$F15="",$G15=""),0,IF(AND(ISNUMBER($E15),ISNUMBER(G15),ISNUMBER(I15),ISNUMBER($J15),ISNUMBER($K15)),$E15*G15+I15+$J15*$K15,NA())))
L16: =IF($B16="",0,IF(AND($E16="",$F16="",$G16=""),0,IF(AND(ISNUMBER($E16),ISNUMBER(F16),ISNUMBER(H16),ISNUMBER($J16),ISNUMBER($K16)),$E16*F16+H16+$J16*$K16,NA()))) | M16: =IF($B16="",0,IF(AND($E16="",$F16="",$G16=""),0,IF(AND(ISNUMBER($E16),ISNUMBER(G16),ISNUMBER(I16),ISNUMBER($J16),ISNUMBER($K16)),$E16*G16+I16+$J16*$K16,NA())))
L17: =IF($B17="",0,IF(AND($E17="",$F17="",$G17=""),0,IF(AND(ISNUMBER($E17),ISNUMBER(F17),ISNUMBER(H17),ISNUMBER($J17),ISNUMBER($K17)),$E17*F17+H17+$J17*$K17,NA()))) | M17: =IF($B17="",0,IF(AND($E17="",$F17="",$G17=""),0,IF(AND(ISNUMBER($E17),ISNUMBER(G17),ISNUMBER(I17),ISNUMBER($J17),ISNUMBER($K17)),$E17*G17+I17+$J17*$K17,NA())))
L18: =IF($B18="",0,IF(AND($E18="",$F18="",$G18=""),0,IF(AND(ISNUMBER($E18),ISNUMBER(F18),ISNUMBER(H18),ISNUMBER($J18),ISNUMBER($K18)),$E18*F18+H18+$J18*$K18,NA()))) | M18: =IF($B18="",0,IF(AND($E18="",$F18="",$G18=""),0,IF(AND(ISNUMBER($E18),ISNUMBER(G18),ISNUMBER(I18),ISNUMBER($J18),ISNUMBER($K18)),$E18*G18+I18+$J18*$K18,NA())))
L19: =IF($B19="",0,IF(AND($E19="",$F19="",$G19=""),0,IF(AND(ISNUMBER($E19),ISNUMBER(F19),ISNUMBER(H19),ISNUMBER($J19),ISNUMBER($K19)),$E19*F19+H19+$J19*$K19,NA()))) | M19: =IF($B19="",0,IF(AND($E19="",$F19="",$G19=""),0,IF(AND(ISNUMBER($E19),ISNUMBER(G19),ISNUMBER(I19),ISNUMBER($J19),ISNUMBER($K19)),$E19*G19+I19+$J19*$K19,NA())))
L20: =IF($B20="",0,IF(AND($E20="",$F20="",$G20=""),0,IF(AND(ISNUMBER($E20),ISNUMBER(F20),ISNUMBER(H20),ISNUMBER($J20),ISNUMBER($K20)),$E20*F20+H20+$J20*$K20,NA()))) | M20: =IF($B20="",0,IF(AND($E20="",$F20="",$G20=""),0,IF(AND(ISNUMBER($E20),ISNUMBER(G20),ISNUMBER(I20),ISNUMBER($J20),ISNUMBER($K20)),$E20*G20+I20+$J20*$K20,NA())))
L21: =IF($B21="",0,IF(AND($E21="",$F21="",$G21=""),0,IF(AND(ISNUMBER($E21),ISNUMBER(F21),ISNUMBER(H21),ISNUMBER($J21),ISNUMBER($K21)),$E21*F21+H21+$J21*$K21,NA()))) | M21: =IF($B21="",0,IF(AND($E21="",$F21="",$G21=""),0,IF(AND(ISNUMBER($E21),ISNUMBER(G21),ISNUMBER(I21),ISNUMBER($J21),ISNUMBER($K21)),$E21*G21+I21+$J21*$K21,NA())))
L22: =IF($B22="",0,IF(AND($E22="",$F22="",$G22=""),0,IF(AND(ISNUMBER($E22),ISNUMBER(F22),ISNUMBER(H22),ISNUMBER($J22),ISNUMBER($K22)),$E22*F22+H22+$J22*$K22,NA()))) | M22: =IF($B22="",0,IF(AND($E22="",$F22="",$G22=""),0,IF(AND(ISNUMBER($E22),ISNUMBER(G22),ISNUMBER(I22),ISNUMBER($J22),ISNUMBER($K22)),$E22*G22+I22+$J22*$K22,NA())))
L23: =IF($B23="",0,IF(AND($E23="",$F23="",$G23=""),0,IF(AND(ISNUMBER($E23),ISNUMBER(F23),ISNUMBER(H23),ISNUMBER($J23),ISNUMBER($K23)),$E23*F23+H23+$J23*$K23,NA()))) | M23: =IF($B23="",0,IF(AND($E23="",$F23="",$G23=""),0,IF(AND(ISNUMBER($E23),ISNUMBER(G23),ISNUMBER(I23),ISNUMBER($J23),ISNUMBER($K23)),$E23*G23+I23+$J23*$K23,NA())))
L24: =IF($B24="",0,IF(AND($E24="",$F24="",$G24=""),0,IF(AND(ISNUMBER($E24),ISNUMBER(F24),ISNUMBER(H24),ISNUMBER($J24),ISNUMBER($K24)),$E24*F24+H24+$J24*$K24,NA()))) | M24: =IF($B24="",0,IF(AND($E24="",$F24="",$G24=""),0,IF(AND(ISNUMBER($E24),ISNUMBER(G24),ISNUMBER(I24),ISNUMBER($J24),ISNUMBER($K24)),$E24*G24+I24+$J24*$K24,NA())))
L25: =IF($B25="",0,IF(AND($E25="",$F25="",$G25=""),0,IF(AND(ISNUMBER($E25),ISNUMBER(F25),ISNUMBER(H25),ISNUMBER($J25),ISNUMBER($K25)),$E25*F25+H25+$J25*$K25,NA()))) | M25: =IF($B25="",0,IF(AND($E25="",$F25="",$G25=""),0,IF(AND(ISNUMBER($E25),ISNUMBER(G25),ISNUMBER(I25),ISNUMBER($J25),ISNUMBER($K25)),$E25*G25+I25+$J25*$K25,NA())))
... L40: =IF($B40="",0,IF(AND($E40="",$F40="",$G40=""),0,IF(AND(ISNUMBER($E40),ISNUMBER(F40),ISNUMBER(H40),ISNUMBER($J40),ISNUMBER($K40)),$E40*F40+H40+$J40*$K40,NA()))) | M40: =IF($B40="",0,IF(AND($E40="",$F40="",$G40=""),0,IF(AND(ISNUMBER($E40),ISNUMBER(G40),ISNUMBER(I40),ISNUMBER($J40),ISNUMBER($K40)),$E40*G40+I40+$J40*$K40,NA())))

Sheet Mobilization_Other
A1: line_id | B1: category | C1: item | D1: basis | E1: unit_cost | F1: qty_base | G1: qty_alt | H1: ext_base | I1: ext_alt | J1: notes
A2: O01 | B2: Mobilization | C2: Mobilize crew and equipment to site | D2: trip | E2: 250 | F2: 1 | G2: 1 | H2: =IF($C2="",0,IF(AND($E2="",$F2="",$G2=""),0,IF(AND(ISNUMBER($E2),ISNUMBER(F2)),$E2*F2,NA()))) | I2: =IF($C2="",0,IF(AND($E2="",$F2="",$G2=""),0,IF(AND(ISNUMBER($E2),ISNUMBER(G2)),$E2*G2,NA())))
A3: O02 | B3: Mobilization | C3: Demobilize | D3: trip | E3: 250 | F3: 1 | G3: 1 | H3: =IF($C3="",0,IF(AND($E3="",$F3="",$G3=""),0,IF(AND(ISNUMBER($E3),ISNUMBER(F3)),$E3*F3,NA()))) | I3: =IF($C3="",0,IF(AND($E3="",$F3="",$G3=""),0,IF(AND(ISNUMBER($E3),ISNUMBER(G3)),$E3*G3,NA())))
A4: O03 | B4: Mobilization | C4: Additional trips (gates, windscreen, punch list) | D4: trip | E4: 250 | F4: 3 | G4: 2 | H4: =IF($C4="",0,IF(AND($E4="",$F4="",$G4=""),0,IF(AND(ISNUMBER($E4),ISNUMBER(F4)),$E4*F4,NA()))) | I4: =IF($C4="",0,IF(AND($E4="",$F4="",$G4=""),0,IF(AND(ISNUMBER($E4),ISNUMBER(G4)),$E4*G4,NA())))
A5: O04 | B5: Mobilization | C5: Truck mileage | D5: mile | E5: 1 | F5: 600 | G5: 480 | H5: =IF($C5="",0,IF(AND($E5="",$F5="",$G5=""),0,IF(AND(ISNUMBER($E5),ISNUMBER(F5)),$E5*F5,NA()))) | I5: =IF($C5="",0,IF(AND($E5="",$F5="",$G5=""),0,IF(AND(ISNUMBER($E5),ISNUMBER(G5)),$E5*G5,NA()))) | J5: Fictional reference estimate; not a vendor quote.
A6: O05 | B6: Mobilization | C6: Per diem / lodging | D6: day | H6: =IF($C6="",0,IF(AND($E6="",$F6="",$G6=""),0,IF(AND(ISNUMBER($E6),ISNUMBER(F6)),$E6*F6,NA()))) | I6: =IF($C6="",0,IF(AND($E6="",$F6="",$G6=""),0,IF(AND(ISNUMBER($E6),ISNUMBER(G6)),$E6*G6,NA())))
A7: O06 | B7: Site | C7: Utility locates (811) and private locate | D7: each | E7: 350 | F7: 1 | G7: 1 | H7: =IF($C7="",0,IF(AND($E7="",$F7="",$G7=""),0,IF(AND(ISNUMBER($E7),ISNUMBER(F7)),$E7*F7,NA()))) | I7: =IF($C7="",0,IF(AND($E7="",$F7="",$G7=""),0,IF(AND(ISNUMBER($E7),ISNUMBER(G7)),$E7*G7,NA()))) | J7: Private utility locate allowance. 811 is free.
A8: O07 | B8: Site | C8: Permit and fees | D8: each | E8: 150 | F8: 1 | G8: 1 | H8: =IF($C8="",0,IF(AND($E8="",$F8="",$G8=""),0,IF(AND(ISNUMBER($E8),ISNUMBER(F8)),$E8*F8,NA()))) | I8: =IF($C8="",0,IF(AND($E8="",$F8="",$G8=""),0,IF(AND(ISNUMBER($E8),ISNUMBER(G8)),$E8*G8,NA()))) | J8: Allowance, jurisdiction dependent.
A9: O08 | B9: Site | C9: Survey / layout subcontract | D9: each | H9: =IF($C9="",0,IF(AND($E9="",$F9="",$G9=""),0,IF(AND(ISNUMBER($E9),ISNUMBER(F9)),$E9*F9,NA()))) | I9: =IF($C9="",0,IF(AND($E9="",$F9="",$G9=""),0,IF(AND(ISNUMBER($E9),ISNUMBER(G9)),$E9*G9,NA())))
A10: O09 | B10: Site | C10: Spoils haul / dumpster | D10: each | E10: 350 | F10: 1 | G10: 1 | H10: =IF($C10="",0,IF(AND($E10="",$F10="",$G10=""),0,IF(AND(ISNUMBER($E10),ISNUMBER(F10)),$E10*F10,NA()))) | I10: =IF($C10="",0,IF(AND($E10="",$F10="",$G10=""),0,IF(AND(ISNUMBER($E10),ISNUMBER(G10)),$E10*G10,NA()))) | J10: One spoils haul allowance. Human estimate; revisit when quantities change.
A11: O10 | B11: Site | C11: Traffic control | D11: day | H11: =IF($C11="",0,IF(AND($E11="",$F11="",$G11=""),0,IF(AND(ISNUMBER($E11),ISNUMBER(F11)),$E11*F11,NA()))) | I11: =IF($C11="",0,IF(AND($E11="",$F11="",$G11=""),0,IF(AND(ISNUMBER($E11),ISNUMBER(G11)),$E11*G11,NA())))
A12: O11 | B12: Site | C12: Temporary fence / site protection | D12: LF | H12: =IF($C12="",0,IF(AND($E12="",$F12="",$G12=""),0,IF(AND(ISNUMBER($E12),ISNUMBER(F12)),$E12*F12,NA()))) | I12: =IF($C12="",0,IF(AND($E12="",$F12="",$G12=""),0,IF(AND(ISNUMBER($E12),ISNUMBER(G12)),$E12*G12,NA())))
A13: O12 | B13: Subcontract | C13: Core drilling / rock | D13: each | H13: =IF($C13="",0,IF(AND($E13="",$F13="",$G13=""),0,IF(AND(ISNUMBER($E13),ISNUMBER(F13)),$E13*F13,NA()))) | I13: =IF($C13="",0,IF(AND($E13="",$F13="",$G13=""),0,IF(AND(ISNUMBER($E13),ISNUMBER(G13)),$E13*G13,NA())))
A14: O13 | B14: Subcontract | C14: Other subcontract: ______ | D14: each | H14: =IF($C14="",0,IF(AND($E14="",$F14="",$G14=""),0,IF(AND(ISNUMBER($E14),ISNUMBER(F14)),$E14*F14,NA()))) | I14: =IF($C14="",0,IF(AND($E14="",$F14="",$G14=""),0,IF(AND(ISNUMBER($E14),ISNUMBER(G14)),$E14*G14,NA())))
A15: O14 | B15: Insurance and bond | C15: Performance and payment bond | D15: LS | H15: =IF($C15="",0,IF(AND($E15="",$F15="",$G15=""),0,IF(AND(ISNUMBER($E15),ISNUMBER(F15)),$E15*F15,NA()))) | I15: =IF($C15="",0,IF(AND($E15="",$F15="",$G15=""),0,IF(AND(ISNUMBER($E15),ISNUMBER(G15)),$E15*G15,NA())))
A16: O15 | B16: Insurance and bond | C16: Project-specific insurance | D16: LS | H16: =IF($C16="",0,IF(AND($E16="",$F16="",$G16=""),0,IF(AND(ISNUMBER($E16),ISNUMBER(F16)),$E16*F16,NA()))) | I16: =IF($C16="",0,IF(AND($E16="",$F16="",$G16=""),0,IF(AND(ISNUMBER($E16),ISNUMBER(G16)),$E16*G16,NA())))
A17: O16 | B17: Other | C17: Contingency items: ______ | D17: each | H17: =IF($C17="",0,IF(AND($E17="",$F17="",$G17=""),0,IF(AND(ISNUMBER($E17),ISNUMBER(F17)),$E17*F17,NA()))) | I17: =IF($C17="",0,IF(AND($E17="",$F17="",$G17=""),0,IF(AND(ISNUMBER($E17),ISNUMBER(G17)),$E17*G17,NA())))
H18: =IF($C18="",0,IF(AND($E18="",$F18="",$G18=""),0,IF(AND(ISNUMBER($E18),ISNUMBER(F18)),$E18*F18,NA()))) | I18: =IF($C18="",0,IF(AND($E18="",$F18="",$G18=""),0,IF(AND(ISNUMBER($E18),ISNUMBER(G18)),$E18*G18,NA())))
H19: =IF($C19="",0,IF(AND($E19="",$F19="",$G19=""),0,IF(AND(ISNUMBER($E19),ISNUMBER(F19)),$E19*F19,NA()))) | I19: =IF($C19="",0,IF(AND($E19="",$F19="",$G19=""),0,IF(AND(ISNUMBER($E19),ISNUMBER(G19)),$E19*G19,NA())))
H20: =IF($C20="",0,IF(AND($E20="",$F20="",$G20=""),0,IF(AND(ISNUMBER($E20),ISNUMBER(F20)),$E20*F20,NA()))) | I20: =IF($C20="",0,IF(AND($E20="",$F20="",$G20=""),0,IF(AND(ISNUMBER($E20),ISNUMBER(G20)),$E20*G20,NA())))
H21: =IF($C21="",0,IF(AND($E21="",$F21="",$G21=""),0,IF(AND(ISNUMBER($E21),ISNUMBER(F21)),$E21*F21,NA()))) | I21: =IF($C21="",0,IF(AND($E21="",$F21="",$G21=""),0,IF(AND(ISNUMBER($E21),ISNUMBER(G21)),$E21*G21,NA())))
H22: =IF($C22="",0,IF(AND($E22="",$F22="",$G22=""),0,IF(AND(ISNUMBER($E22),ISNUMBER(F22)),$E22*F22,NA()))) | I22: =IF($C22="",0,IF(AND($E22="",$F22="",$G22=""),0,IF(AND(ISNUMBER($E22),ISNUMBER(G22)),$E22*G22,NA())))
H23: =IF($C23="",0,IF(AND($E23="",$F23="",$G23=""),0,IF(AND(ISNUMBER($E23),ISNUMBER(F23)),$E23*F23,NA()))) | I23: =IF($C23="",0,IF(AND($E23="",$F23="",$G23=""),0,IF(AND(ISNUMBER($E23),ISNUMBER(G23)),$E23*G23,NA())))
H24: =IF($C24="",0,IF(AND($E24="",$F24="",$G24=""),0,IF(AND(ISNUMBER($E24),ISNUMBER(F24)),$E24*F24,NA()))) | I24: =IF($C24="",0,IF(AND($E24="",$F24="",$G24=""),0,IF(AND(ISNUMBER($E24),ISNUMBER(G24)),$E24*G24,NA())))
H25: =IF($C25="",0,IF(AND($E25="",$F25="",$G25=""),0,IF(AND(ISNUMBER($E25),ISNUMBER(F25)),$E25*F25,NA()))) | I25: =IF($C25="",0,IF(AND($E25="",$F25="",$G25=""),0,IF(AND(ISNUMBER($E25),ISNUMBER(G25)),$E25*G25,NA())))
H26: =IF($C26="",0,IF(AND($E26="",$F26="",$G26=""),0,IF(AND(ISNUMBER($E26),ISNUMBER(F26)),$E26*F26,NA()))) | I26: =IF($C26="",0,IF(AND($E26="",$F26="",$G26=""),0,IF(AND(ISNUMBER($E26),ISNUMBER(G26)),$E26*G26,NA())))
H27: =IF($C27="",0,IF(AND($E27="",$F27="",$G27=""),0,IF(AND(ISNUMBER($E27),ISNUMBER(F27)),$E27*F27,NA()))) | I27: =IF($C27="",0,IF(AND($E27="",$F27="",$G27=""),0,IF(AND(ISNUMBER($E27),ISNUMBER(G27)),$E27*G27,NA())))
H28: =IF($C28="",0,IF(AND($E28="",$F28="",$G28=""),0,IF(AND(ISNUMBER($E28),ISNUMBER(F28)),$E28*F28,NA()))) | I28: =IF($C28="",0,IF(AND($E28="",$F28="",$G28=""),0,IF(AND(ISNUMBER($E28),ISNUMBER(G28)),$E28*G28,NA())))
H29: =IF($C29="",0,IF(AND($E29="",$F29="",$G29=""),0,IF(AND(ISNUMBER($E29),ISNUMBER(F29)),$E29*F29,NA()))) | I29: =IF($C29="",0,IF(AND($E29="",$F29="",$G29=""),0,IF(AND(ISNUMBER($E29),ISNUMBER(G29)),$E29*G29,NA())))
... H60: =IF($C60="",0,IF(AND($E60="",$F60="",$G60=""),0,IF(AND(ISNUMBER($E60),ISNUMBER(F60)),$E60*F60,NA()))) | I60: =IF($C60="",0,IF(AND($E60="",$F60="",$G60=""),0,IF(AND(ISNUMBER($E60),ISNUMBER(G60)),$E60*G60,NA())))

Sheet Services
A1: service_id | B1: service | C1: uom | D1: unit_cost | E1: vendor | F1: price_date | G1: source_url_or_sku | H1: qty_base | I1: qty_alt | J1: ext_base | K1: ext_alt | L1: notes
A2: S01 | B2: Core drilling through pavement and base, per footing hole | C2: EA | D2: 42 | E2: Reference estimate | F2: 46307 | G2: reference estimate | H2: =IF($A2="","",IF(INDEX(Takeoff_In!$D$2:$D$300,MATCH($A2,Takeoff_In!$A$2:$A$300,0))="",NA(),INDEX(Takeoff_In!$D$2:$D$300,MATCH($A2,Takeoff_In!$A$2:$A$300,0)))) | I2: =IF($A2="","",IF(INDEX(Takeoff_In!$E$2:$E$300,MATCH($A2,Takeoff_In!$A$2:$A$300,0))="",NA(),INDEX(Takeoff_In!$E$2:$E$300,MATCH($A2,Takeoff_In!$A$2:$A$300,0)))) | J2: =IF($A2="","",IF(ISNUMBER($D2),H2*$D2,NA())) | K2: =IF($A2="","",IF(ISNUMBER($D2),I2*$D2,NA())) | L2: Subcontracted service. Not a material: no sales tax is applied to it.
H3: =IF($A3="","",IF(INDEX(Takeoff_In!$D$2:$D$300,MATCH($A3,Takeoff_In!$A$2:$A$300,0))="",NA(),INDEX(Takeoff_In!$D$2:$D$300,MATCH($A3,Takeoff_In!$A$2:$A$300,0)))) | I3: =IF($A3="","",IF(INDEX(Takeoff_In!$E$2:$E$300,MATCH($A3,Takeoff_In!$A$2:$A$300,0))="",NA(),INDEX(Takeoff_In!$E$2:$E$300,MATCH($A3,Takeoff_In!$A$2:$A$300,0)))) | J3: =IF($A3="","",IF(ISNUMBER($D3),H3*$D3,NA())) | K3: =IF($A3="","",IF(ISNUMBER($D3),I3*$D3,NA()))
H4: =IF($A4="","",IF(INDEX(Takeoff_In!$D$2:$D$300,MATCH($A4,Takeoff_In!$A$2:$A$300,0))="",NA(),INDEX(Takeoff_In!$D$2:$D$300,MATCH($A4,Takeoff_In!$A$2:$A$300,0)))) | I4: =IF($A4="","",IF(INDEX(Takeoff_In!$E$2:$E$300,MATCH($A4,Takeoff_In!$A$2:$A$300,0))="",NA(),INDEX(Takeoff_In!$E$2:$E$300,MATCH($A4,Takeoff_In!$A$2:$A$300,0)))) | J4: =IF($A4="","",IF(ISNUMBER($D4),H4*$D4,NA())) | K4: =IF($A4="","",IF(ISNUMBER($D4),I4*$D4,NA()))
H5: =IF($A5="","",IF(INDEX(Takeoff_In!$D$2:$D$300,MATCH($A5,Takeoff_In!$A$2:$A$300,0))="",NA(),INDEX(Takeoff_In!$D$2:$D$300,MATCH($A5,Takeoff_In!$A$2:$A$300,0)))) | I5: =IF($A5="","",IF(INDEX(Takeoff_In!$E$2:$E$300,MATCH($A5,Takeoff_In!$A$2:$A$300,0))="",NA(),INDEX(Takeoff_In!$E$2:$E$300,MATCH($A5,Takeoff_In!$A$2:$A$300,0)))) | J5: =IF($A5="","",IF(ISNUMBER($D5),H5*$D5,NA())) | K5: =IF($A5="","",IF(ISNUMBER($D5),I5*$D5,NA()))
H6: =IF($A6="","",IF(INDEX(Takeoff_In!$D$2:$D$300,MATCH($A6,Takeoff_In!$A$2:$A$300,0))="",NA(),INDEX(Takeoff_In!$D$2:$D$300,MATCH($A6,Takeoff_In!$A$2:$A$300,0)))) | I6: =IF($A6="","",IF(INDEX(Takeoff_In!$E$2:$E$300,MATCH($A6,Takeoff_In!$A$2:$A$300,0))="",NA(),INDEX(Takeoff_In!$E$2:$E$300,MATCH($A6,Takeoff_In!$A$2:$A$300,0)))) | J6: =IF($A6="","",IF(ISNUMBER($D6),H6*$D6,NA())) | K6: =IF($A6="","",IF(ISNUMBER($D6),I6*$D6,NA()))
H7: =IF($A7="","",IF(INDEX(Takeoff_In!$D$2:$D$300,MATCH($A7,Takeoff_In!$A$2:$A$300,0))="",NA(),INDEX(Takeoff_In!$D$2:$D$300,MATCH($A7,Takeoff_In!$A$2:$A$300,0)))) | I7: =IF($A7="","",IF(INDEX(Takeoff_In!$E$2:$E$300,MATCH($A7,Takeoff_In!$A$2:$A$300,0))="",NA(),INDEX(Takeoff_In!$E$2:$E$300,MATCH($A7,Takeoff_In!$A$2:$A$300,0)))) | J7: =IF($A7="","",IF(ISNUMBER($D7),H7*$D7,NA())) | K7: =IF($A7="","",IF(ISNUMBER($D7),I7*$D7,NA()))
H8: =IF($A8="","",IF(INDEX(Takeoff_In!$D$2:$D$300,MATCH($A8,Takeoff_In!$A$2:$A$300,0))="",NA(),INDEX(Takeoff_In!$D$2:$D$300,MATCH($A8,Takeoff_In!$A$2:$A$300,0)))) | I8: =IF($A8="","",IF(INDEX(Takeoff_In!$E$2:$E$300,MATCH($A8,Takeoff_In!$A$2:$A$300,0))="",NA(),INDEX(Takeoff_In!$E$2:$E$300,MATCH($A8,Takeoff_In!$A$2:$A$300,0)))) | J8: =IF($A8="","",IF(ISNUMBER($D8),H8*$D8,NA())) | K8: =IF($A8="","",IF(ISNUMBER($D8),I8*$D8,NA()))
H9: =IF($A9="","",IF(INDEX(Takeoff_In!$D$2:$D$300,MATCH($A9,Takeoff_In!$A$2:$A$300,0))="",NA(),INDEX(Takeoff_In!$D$2:$D$300,MATCH($A9,Takeoff_In!$A$2:$A$300,0)))) | I9: =IF($A9="","",IF(INDEX(Takeoff_In!$E$2:$E$300,MATCH($A9,Takeoff_In!$A$2:$A$300,0))="",NA(),INDEX(Takeoff_In!$E$2:$E$300,MATCH($A9,Takeoff_In!$A$2:$A$300,0)))) | J9: =IF($A9="","",IF(ISNUMBER($D9),H9*$D9,NA())) | K9: =IF($A9="","",IF(ISNUMBER($D9),I9*$D9,NA()))
H10: =IF($A10="","",IF(INDEX(Takeoff_In!$D$2:$D$300,MATCH($A10,Takeoff_In!$A$2:$A$300,0))="",NA(),INDEX(Takeoff_In!$D$2:$D$300,MATCH($A10,Takeoff_In!$A$2:$A$300,0)))) | I10: =IF($A10="","",IF(INDEX(Takeoff_In!$E$2:$E$300,MATCH($A10,Takeoff_In!$A$2:$A$300,0))="",NA(),INDEX(Takeoff_In!$E$2:$E$300,MATCH($A10,Takeoff_In!$A$2:$A$300,0)))) | J10: =IF($A10="","",IF(ISNUMBER($D10),H10*$D10,NA())) | K10: =IF($A10="","",IF(ISNUMBER($D10),I10*$D10,NA()))
H11: =IF($A11="","",IF(INDEX(Takeoff_In!$D$2:$D$300,MATCH($A11,Takeoff_In!$A$2:$A$300,0))="",NA(),INDEX(Takeoff_In!$D$2:$D$300,MATCH($A11,Takeoff_In!$A$2:$A$300,0)))) | I11: =IF($A11="","",IF(INDEX(Takeoff_In!$E$2:$E$300,MATCH($A11,Takeoff_In!$A$2:$A$300,0))="",NA(),INDEX(Takeoff_In!$E$2:$E$300,MATCH($A11,Takeoff_In!$A$2:$A$300,0)))) | J11: =IF($A11="","",IF(ISNUMBER($D11),H11*$D11,NA())) | K11: =IF($A11="","",IF(ISNUMBER($D11),I11*$D11,NA()))
H12: =IF($A12="","",IF(INDEX(Takeoff_In!$D$2:$D$300,MATCH($A12,Takeoff_In!$A$2:$A$300,0))="",NA(),INDEX(Takeoff_In!$D$2:$D$300,MATCH($A12,Takeoff_In!$A$2:$A$300,0)))) | I12: =IF($A12="","",IF(INDEX(Takeoff_In!$E$2:$E$300,MATCH($A12,Takeoff_In!$A$2:$A$300,0))="",NA(),INDEX(Takeoff_In!$E$2:$E$300,MATCH($A12,Takeoff_In!$A$2:$A$300,0)))) | J12: =IF($A12="","",IF(ISNUMBER($D12),H12*$D12,NA())) | K12: =IF($A12="","",IF(ISNUMBER($D12),I12*$D12,NA()))
H13: =IF($A13="","",IF(INDEX(Takeoff_In!$D$2:$D$300,MATCH($A13,Takeoff_In!$A$2:$A$300,0))="",NA(),INDEX(Takeoff_In!$D$2:$D$300,MATCH($A13,Takeoff_In!$A$2:$A$300,0)))) | I13: =IF($A13="","",IF(INDEX(Takeoff_In!$E$2:$E$300,MATCH($A13,Takeoff_In!$A$2:$A$300,0))="",NA(),INDEX(Takeoff_In!$E$2:$E$300,MATCH($A13,Takeoff_In!$A$2:$A$300,0)))) | J13: =IF($A13="","",IF(ISNUMBER($D13),H13*$D13,NA())) | K13: =IF($A13="","",IF(ISNUMBER($D13),I13*$D13,NA()))
H14: =IF($A14="","",IF(INDEX(Takeoff_In!$D$2:$D$300,MATCH($A14,Takeoff_In!$A$2:$A$300,0))="",NA(),INDEX(Takeoff_In!$D$2:$D$300,MATCH($A14,Takeoff_In!$A$2:$A$300,0)))) | I14: =IF($A14="","",IF(INDEX(Takeoff_In!$E$2:$E$300,MATCH($A14,Takeoff_In!$A$2:$A$300,0))="",NA(),INDEX(Takeoff_In!$E$2:$E$300,MATCH($A14,Takeoff_In!$A$2:$A$300,0)))) | J14: =IF($A14="","",IF(ISNUMBER($D14),H14*$D14,NA())) | K14: =IF($A14="","",IF(ISNUMBER($D14),I14*$D14,NA()))
... H40: =IF($A40="","",IF(INDEX(Takeoff_In!$D$2:$D$300,MATCH($A40,Takeoff_In!$A$2:$A$300,0))="",NA(),INDEX(Takeoff_In!$D$2:$D$300,MATCH($A40,Takeoff_In!$A$2:$A$300,0)))) | I40: =IF($A40="","",IF(INDEX(Takeoff_In!$E$2:$E$300,MATCH($A40,Takeoff_In!$A$2:$A$300,0))="",NA(),INDEX(Takeoff_In!$E$2:$E$300,MATCH($A40,Takeoff_In!$A$2:$A$300,0)))) | J40: =IF($A40="","",IF(ISNUMBER($D40),H40*$D40,NA())) | K40: =IF($A40="","",IF(ISNUMBER($D40),I40*$D40,NA()))

Sheet Summary
A1: Cost roll-up | B1: Base bid | C1: Alt A-1 | D1: Notes
A2: Materials (order qty x unit price) | B2: =SUM(Materials!O2:O200) | C2: =SUM(Materials!P2:P200) | D2: Fictional reference estimate; not a vendor quote.
A3: Sales tax on materials | B3: =B2*$B$16 | C3: =C2*$B$16 | D3: Rate in B16.
A4: Labor | B4: =SUM(Labor!L2:L60) | C4: =SUM(Labor!M2:M60) | D4: Labor sheet.
A5: Equipment | B5: =SUM(Equipment!L2:L40) | C5: =SUM(Equipment!M2:M40) | D5: Equipment sheet.
A6: Mobilization, services and other | B6: =SUM(Mobilization_Other!H2:H60)+SUM(Services!J2:J40) | C6: =SUM(Mobilization_Other!I2:I60)+SUM(Services!K2:K40) | D6: Mobilization_Other and Services sheets.
A7: Direct cost | B7: =SUM(B2:B6) | C7: =SUM(C2:C6)
A8: Overhead | B8: =B7*$B$17 | C8: =C7*$B$17 | D8: Rate in B17.
A9: Contingency | B9: =B7*$B$18 | C9: =C7*$B$18 | D9: Rate in B18.
A10: Subtotal before profit | B10: =B7+B8+B9 | C10: =C7+C8+C9
A11: Profit | B11: =B10*$B$19 | C11: =C10*$B$19 | D11: Rate in B19.
A12: Price | B12: =B10+B11 | C12: =C10+C11 | D12: Computed by code from the sheets. No model writes any dollar figure.
A13: Price per LF of fence (Type A + B) | B13: =B12/(INDEX(Takeoff_In!$D$2:$D$300,MATCH("D01",Takeoff_In!$A$2:$A$300,0))+INDEX(Takeoff_In!$D$2:$D$300,MATCH("D02",Takeoff_In!$A$2:$A$300,0))) | C13: =C12/(INDEX(Takeoff_In!$E$2:$E$300,MATCH("D01",Takeoff_In!$A$2:$A$300,0))+INDEX(Takeoff_In!$E$2:$E$300,MATCH("D02",Takeoff_In!$A$2:$A$300,0))) | D13: Uses D01 + D02.
A15: Rates (read from Meta sheet; edit them there)
A16: Sales tax on materials | B16: =Meta!B8
A17: Overhead | B17: =Meta!B9
A18: Contingency | B18: =Meta!B10
A19: Profit | B19: =Meta!B11
A21: Checks
A22: Materials lines with no numeric unit price | B22: =SUMPRODUCT((Materials!A2:A200<>"")*(1-ISNUMBER(Materials!F2:F200)))
A23: Takeoff keys with no qty written | B23: =SUMPRODUCT((Takeoff_In!A2:A300<>"")*(Takeoff_In!D2:D300=""))
A24: Labor tasks with qty but no production rate | B24: =SUMPRODUCT((Labor!C2:C60<>"")*(Labor!F2:F60=""))
A25: Labor tasks with no crew | B25: =SUMPRODUCT((Labor!C2:C60<>"")*(Labor!E2:E60=""))
A26: Labor crew-hours, base / crew-days at 8 hr | B26: =SUM(Labor!I2:I60) | C26: =B26/8
A27: Takeoff keys with no alt qty written | B27: =SUMPRODUCT((Takeoff_In!A2:A300<>"")*(Takeoff_In!E2:E300=""))
A28: Package status (base bid) | B28: =IF(AND(B22=0,B23=0,B24=0,B25=0,ISNUMBER(B12)),"COMPLETE","INCOMPLETE - DO NOT QUOTE") | D28: Python engine is authoritative for released prices; this sheet is for inspection and reconciliation.
